{"result":0,"data":{"total":3821,"city":{"cityName":"宁波","cityId":"330200"},"totalPage":255,"recruitType":"工作类型","keyword":"","list":[{"jobName":"技术员","pubEdu":"专科","hasVip":0,"salary":"面议","hasComment":0,"jobHref":"//job.dajie.com/4bbaf09c-eca8-48d9-a287-12468aef0012.html?jobsearch\u003d0\u0026pagereferer\u003dblank\u0026keyword\u003dnull\u0026clicktype\u003djob","compName":"万维环球科技(深圳)有限公司宁波分公司","pubCity":"宁波","pubEx":"不限","hasIcon":0,"time":"2016-10-19","liHref":"//job.dajie.com/4bbaf09c-eca8-48d9-a287-12468aef0012.html?jobsearch\u003d0\u0026pagereferer\u003dblank\u0026keyword\u003dnull\u0026clicktype\u003dblank","imgSrc":"//fs1.dajie.com/corplogo/50x50.png"},{"jobName":"英文理单员","pubEdu":"专科","hasVip":0,"salary":"面议","hasComment":0,"jobHref":"//job.dajie.com/9b0b8708-f136-429f-a337-65b98ca2e368.html?jobsearch\u003d0\u0026pagereferer\u003dblank\u0026keyword\u003dnull\u0026clicktype\u003djob","compName":"宁波市鄞州钢盈服饰有限公司","pubCity":"宁波","pubEx":"3年以上","hasIcon":0,"time":"2016-10-19","liHref":"//job.dajie.com/9b0b8708-f136-429f-a337-65b98ca2e368.html?jobsearch\u003d0\u0026pagereferer\u003dblank\u0026keyword\u003dnull\u0026clicktype\u003dblank","imgSrc":"//fs1.dajie.com/corplogo/50x50.png"},{"jobName":"银行渠道销售专员（无责任底薪5000元+免费提供住宿+六险一金）","pubEdu":"专科","hasVip":0,"salary":"8000元/月","hasComment":0,"jobHref":"//job.dajie.com/09543719-0f6e-46fc-9a4f-e9949e122d74.html?jobsearch\u003d0\u0026pagereferer\u003dblank\u0026keyword\u003dnull\u0026clicktype\u003djob","compName":"国金黄金股份有限公司","pubCity":"宁波","pubEx":"不限","hasIcon":0,"time":"2016-10-19","liHref":"//job.dajie.com/09543719-0f6e-46fc-9a4f-e9949e122d74.html?jobsearch\u003d0\u0026pagereferer\u003dblank\u0026keyword\u003dnull\u0026clicktype\u003dblank","imgSrc":"//fs1.dajie.com/corplogo/50x50.png"},{"jobName":"客户维护员","pubEdu":"专科","hasVip":0,"salary":"4000元/月","hasComment":0,"jobHref":"//job.dajie.com/81ac7ee3-c9c8-4d07-a197-4f41ce11b1b7.html?jobsearch\u003d0\u0026pagereferer\u003dblank\u0026keyword\u003dnull\u0026clicktype\u003djob","compName":"宁波市鄞州重创广告服务有限公司","pubCity":"宁波","pubEx":"1年以上","hasIcon":0,"time":"2016-10-19","liHref":"//job.dajie.com/81ac7ee3-c9c8-4d07-a197-4f41ce11b1b7.html?jobsearch\u003d0\u0026pagereferer\u003dblank\u0026keyword\u003dnull\u0026clicktype\u003dblank","imgSrc":"//fs1.dajie.com/corplogo/50x50.png"},{"jobName":"司机兼行政人员","hasVip":0,"salary":"面议","hasComment":0,"jobHref":"//job.dajie.com/89178f15-c99c-4cfb-b97e-aa81bb276f6b.html?jobsearch\u003d0\u0026pagereferer\u003dblank\u0026keyword\u003dnull\u0026clicktype\u003djob","compName":"宁波量化硅谷投资管理有限公司","pubCity":"宁波","pubEx":"不限","hasIcon":0,"time":"2016-10-19","liHref":"//job.dajie.com/89178f15-c99c-4cfb-b97e-aa81bb276f6b.html?jobsearch\u003d0\u0026pagereferer\u003dblank\u0026keyword\u003dnull\u0026clicktype\u003dblank","imgSrc":"//fs1.dajie.com/corplogo/50x50.png"},{"jobName":"驾驶员","hasVip":0,"salary":"4000元/月","hasComment":0,"jobHref":"//job.dajie.com/83e19385-e4e9-4e19-9783-ef2e18794574.html?jobsearch\u003d0\u0026pagereferer\u003dblank\u0026keyword\u003dnull\u0026clicktype\u003djob","compName":"天地华宇","pubCity":"宁波","pubEx":"3年以上","hasIcon":0,"time":"2016-10-19","liHref":"//job.dajie.com/83e19385-e4e9-4e19-9783-ef2e18794574.html?jobsearch\u003d0\u0026pagereferer\u003dblank\u0026keyword\u003dnull\u0026clicktype\u003dblank","imgSrc":"//fs1.dajie.com/corplogo/50x50.png"},{"jobName":"PHP","pubEdu":"专科","hasVip":0,"salary":"4000元/月","hasComment":0,"jobHref":"//job.dajie.com/62fa464a-6975-4883-a923-5a53e905bcf8.html?jobsearch\u003d0\u0026pagereferer\u003dblank\u0026keyword\u003dnull\u0026clicktype\u003djob","compName":"宁波蒲公英信息科技有限公司","pubCity":"宁波","pubEx":"1年以上","hasIcon":0,"time":"2016-10-19","liHref":"//job.dajie.com/62fa464a-6975-4883-a923-5a53e905bcf8.html?jobsearch\u003d0\u0026pagereferer\u003dblank\u0026keyword\u003dnull\u0026clicktype\u003dblank","imgSrc":"//fs1.dajie.com/corplogo/50x50.png"},{"jobName":"微商城推广员","hasVip":0,"salary":"面议","hasComment":0,"jobHref":"//job.dajie.com/5eb8478e-9dd6-4b28-9bad-48beb2f7234e.html?jobsearch\u003d0\u0026pagereferer\u003dblank\u0026keyword\u003dnull\u0026clicktype\u003djob","compName":"宁波微聚致远贸易有限公司","pubCity":"宁波","pubEx":"不限","hasIcon":0,"time":"2016-10-19","liHref":"//job.dajie.com/5eb8478e-9dd6-4b28-9bad-48beb2f7234e.html?jobsearch\u003d0\u0026pagereferer\u003dblank\u0026keyword\u003dnull\u0026clicktype\u003dblank","imgSrc":"//fs1.dajie.com/corplogo/50x50.png"},{"jobName":"客户代表","pubEdu":"专科","hasVip":0,"salary":"6000元/月","hasComment":0,"jobHref":"//job.dajie.com/ab1d6c13-eb5e-453f-84b7-56b63fc09fac.html?jobsearch\u003d0\u0026pagereferer\u003dblank\u0026keyword\u003dnull\u0026clicktype\u003djob","compName":"浙江三众聚惠控股有限公司","pubCity":"宁波","pubEx":"不限","hasIcon":0,"time":"2016-10-19","liHref":"//job.dajie.com/ab1d6c13-eb5e-453f-84b7-56b63fc09fac.html?jobsearch\u003d0\u0026pagereferer\u003dblank\u0026keyword\u003dnull\u0026clicktype\u003dblank","imgSrc":"//fs1.dajie.com/corplogo/50x50.png"},{"jobName":"工艺副部长（汽车组合开关生产）","pubEdu":"专科","hasVip":0,"salary":"面议","hasComment":0,"jobHref":"//job.dajie.com/25261ea4-f72f-4424-ac76-8a2722c08d78.html?jobsearch\u003d0\u0026pagereferer\u003dblank\u0026keyword\u003dnull\u0026clicktype\u003djob","compName":"苏州扬信德汽车零部件有限公司","pubCity":"宁波","pubEx":"8年以上","hasIcon":0,"time":"2016-10-19","liHref":"//job.dajie.com/25261ea4-f72f-4424-ac76-8a2722c08d78.html?jobsearch\u003d0\u0026pagereferer\u003dblank\u0026keyword\u003dnull\u0026clicktype\u003dblank","imgSrc":"//fs1.dajie.com/corplogo/50x50.png"},{"jobName":"线上客服（双休）","pubEdu":"专科","hasVip":0,"salary":"2000元/月","hasComment":0,"jobHref":"//job.dajie.com/75a45927-3928-4cde-93f8-e02a6ecfea4c.html?jobsearch\u003d0\u0026pagereferer\u003dblank\u0026keyword\u003dnull\u0026clicktype\u003djob","compName":"宁波壹鑫广告传媒有限公司","pubCity":"宁波","pubEx":"不限","hasIcon":0,"time":"2016-10-19","liHref":"//job.dajie.com/75a45927-3928-4cde-93f8-e02a6ecfea4c.html?jobsearch\u003d0\u0026pagereferer\u003dblank\u0026keyword\u003dnull\u0026clicktype\u003dblank","imgSrc":"//fs1.dajie.com/corplogo/50x50.png"},{"jobName":"快消品销售专员4-6k+免费住宿+提成+五险一金","hasVip":0,"salary":"6000元/月","hasComment":0,"jobHref":"//job.dajie.com/77e0e576-c395-4dc6-8ba5-ee4a4e9416e4.html?jobsearch\u003d0\u0026pagereferer\u003dblank\u0026keyword\u003dnull\u0026clicktype\u003djob","compName":"宁波景祥环保科技有限公司","pubCity":"宁波","pubEx":"不限","hasIcon":0,"time":"2016-10-19","liHref":"//job.dajie.com/77e0e576-c395-4dc6-8ba5-ee4a4e9416e4.html?jobsearch\u003d0\u0026pagereferer\u003dblank\u0026keyword\u003dnull\u0026clicktype\u003dblank","imgSrc":"//fs1.dajie.com/corplogo/50x50.png"},{"jobName":"外贸/贸易专员/助理  ，外贸业务助理","pubEdu":"专科","hasVip":0,"salary":"面议","hasComment":0,"jobHref":"//job.dajie.com/7643a9cf-b0a2-414d-aca2-f36b7df61ab9.html?jobsearch\u003d0\u0026pagereferer\u003dblank\u0026keyword\u003dnull\u0026clicktype\u003djob","compName":"宁波市鄞州钢盈服饰有限公司","pubCity":"宁波","pubEx":"不限","hasIcon":0,"time":"2016-10-19","liHref":"//job.dajie.com/7643a9cf-b0a2-414d-aca2-f36b7df61ab9.html?jobsearch\u003d0\u0026pagereferer\u003dblank\u0026keyword\u003dnull\u0026clicktype\u003dblank","imgSrc":"//fs1.dajie.com/corplogo/50x50.png"},{"jobName":"手机APP试玩兼职（每小时30，无需经验，在家可做）","hasVip":0,"salary":"4000元/月","hasComment":0,"jobHref":"//job.dajie.com/7728bf82-6f6d-4f3a-a550-7a5a3bc34329.html?jobsearch\u003d0\u0026pagereferer\u003dblank\u0026keyword\u003dnull\u0026clicktype\u003djob","compName":"三思电子科技有限公司","pubCity":"宁波","pubEx":"不限","hasIcon":0,"time":"2016-10-19","liHref":"//job.dajie.com/7728bf82-6f6d-4f3a-a550-7a5a3bc34329.html?jobsearch\u003d0\u0026pagereferer\u003dblank\u0026keyword\u003dnull\u0026clicktype\u003dblank","imgSrc":"//fs1.dajie.com/corplogo/50x50.png"},{"jobName":"俄语翻译 外贸业务员（需面试，地点浙江宁波）","pubEdu":"本科","hasVip":0,"salary":"4000元/月","hasComment":0,"jobHref":"//job.dajie.com/2057b7ba-b87a-4ce1-af19-4d74db27b694.html?jobsearch\u003d0\u0026pagereferer\u003dblank\u0026keyword\u003dnull\u0026clicktype\u003djob","compName":"宁波一翔进出口有限公司","pubCity":"宁波","pubEx":"不限","hasIcon":0,"time":"2016-10-19","liHref":"//job.dajie.com/2057b7ba-b87a-4ce1-af19-4d74db27b694.html?jobsearch\u003d0\u0026pagereferer\u003dblank\u0026keyword\u003dnull\u0026clicktype\u003dblank","imgSrc":"//fs1.dajie.com/corplogo/50x50.png"}],"salary":"薪资范围","nowPage":132}}