{"result":0,"data":{"total":3821,"city":{"cityName":"宁波","cityId":"330200"},"totalPage":255,"recruitType":"工作类型","keyword":"","list":[{"jobName":"项目经理","pubEdu":"本科","hasVip":0,"salary":"8000元/月","hasComment":0,"jobHref":"//job.dajie.com/50ffff1f-fb7e-4597-8889-778e279c5f54.html?jobsearch\u003d0\u0026pagereferer\u003dblank\u0026keyword\u003dnull\u0026clicktype\u003djob","compName":"宁波睿诺电子科技有限公司","pubCity":"宁波","pubEx":"3年以上","hasIcon":0,"time":"2016-10-17","liHref":"//job.dajie.com/50ffff1f-fb7e-4597-8889-778e279c5f54.html?jobsearch\u003d0\u0026pagereferer\u003dblank\u0026keyword\u003dnull\u0026clicktype\u003dblank","imgSrc":"//fs1.dajie.com/corplogo/50x50.png"},{"jobName":"分公司总经理/合伙人（培训后派往外地）","hasVip":0,"salary":"10000元/月","hasComment":0,"jobHref":"//job.dajie.com/32f89d44-498b-4cfe-9b68-e545739825a5.html?jobsearch\u003d0\u0026pagereferer\u003dblank\u0026keyword\u003dnull\u0026clicktype\u003djob","compName":"浙江天之江集团有限公司","pubCity":"宁波","pubEx":"5年以上","hasIcon":0,"time":"2016-10-17","liHref":"//job.dajie.com/32f89d44-498b-4cfe-9b68-e545739825a5.html?jobsearch\u003d0\u0026pagereferer\u003dblank\u0026keyword\u003dnull\u0026clicktype\u003dblank","imgSrc":"//fs1.dajie.com/corplogo/50x50.png"},{"jobName":"课程顾问/销售/咨询顾问（无责任底薪3500起+提成+奖金）","pubEdu":"专科","hasVip":0,"salary":"8000元/月","hasComment":0,"jobHref":"//job.dajie.com/60c0e330-1b75-4a45-b145-d2cb35b96a93.html?jobsearch\u003d0\u0026pagereferer\u003dblank\u0026keyword\u003dnull\u0026clicktype\u003djob","compName":"宁波市赢在起点教育科技有限公司","pubCity":"宁波","pubEx":"1年以上","hasIcon":0,"time":"2016-10-17","liHref":"//job.dajie.com/60c0e330-1b75-4a45-b145-d2cb35b96a93.html?jobsearch\u003d0\u0026pagereferer\u003dblank\u0026keyword\u003dnull\u0026clicktype\u003dblank","imgSrc":"//fs1.dajie.com/corplogo/50x50.png"},{"jobName":"中心校长/中心主任/销售经理（年薪30万起）","pubEdu":"专科","hasVip":0,"salary":"面议","hasComment":0,"jobHref":"//job.dajie.com/59bf3a12-dc51-41ea-8dcd-386a674af824.html?jobsearch\u003d0\u0026pagereferer\u003dblank\u0026keyword\u003dnull\u0026clicktype\u003djob","compName":"宁波市赢在起点教育科技有限公司","pubCity":"宁波","pubEx":"3年以上","hasIcon":0,"time":"2016-10-17","liHref":"//job.dajie.com/59bf3a12-dc51-41ea-8dcd-386a674af824.html?jobsearch\u003d0\u0026pagereferer\u003dblank\u0026keyword\u003dnull\u0026clicktype\u003dblank","imgSrc":"//fs1.dajie.com/corplogo/50x50.png"},{"jobName":"人事行政专员","hasVip":0,"salary":"4000元/月","hasComment":0,"jobHref":"//job.dajie.com/5a877e4b-817e-4d81-94ee-539b101746ba.html?jobsearch\u003d0\u0026pagereferer\u003dblank\u0026keyword\u003dnull\u0026clicktype\u003djob","compName":"一县一品(北京)电子商务有限公司","pubCity":"宁波","pubEx":"不限","hasIcon":0,"time":"2016-10-17","liHref":"//job.dajie.com/5a877e4b-817e-4d81-94ee-539b101746ba.html?jobsearch\u003d0\u0026pagereferer\u003dblank\u0026keyword\u003dnull\u0026clicktype\u003dblank","imgSrc":"//fs1.dajie.com/corplogo/50x50.png"},{"jobName":"商业地产策划经理","hasVip":0,"salary":"8000元/月","hasComment":0,"jobHref":"//job.dajie.com/726c7ad1-5179-4463-b622-ec9348647baa.html?jobsearch\u003d0\u0026pagereferer\u003dblank\u0026keyword\u003dnull\u0026clicktype\u003djob","compName":"一县一品(北京)电子商务有限公司","pubCity":"宁波","pubEx":"不限","hasIcon":0,"time":"2016-10-17","liHref":"//job.dajie.com/726c7ad1-5179-4463-b622-ec9348647baa.html?jobsearch\u003d0\u0026pagereferer\u003dblank\u0026keyword\u003dnull\u0026clicktype\u003dblank","imgSrc":"//fs1.dajie.com/corplogo/50x50.png"},{"jobName":"✅手机兼职试玩app【一单一结】","hasVip":0,"salary":"4000元/月","hasComment":0,"jobHref":"//job.dajie.com/c03577d5-9373-4c30-b501-f0615388512f.html?jobsearch\u003d0\u0026pagereferer\u003dblank\u0026keyword\u003dnull\u0026clicktype\u003djob","compName":"山东缘如水网络科技有限公司","pubCity":"宁波","pubEx":"不限","hasIcon":0,"time":"2016-10-17","liHref":"//job.dajie.com/c03577d5-9373-4c30-b501-f0615388512f.html?jobsearch\u003d0\u0026pagereferer\u003dblank\u0026keyword\u003dnull\u0026clicktype\u003dblank","imgSrc":"//fs1.dajie.com/corplogo/50x50.png"},{"jobName":"新媒体运营总监","pubEdu":"本科","hasVip":0,"salary":"6000元/月","hasComment":0,"jobHref":"//job.dajie.com/f7e7e5b3-1e01-43db-bcf9-4ab37f5afc59.html?jobsearch\u003d0\u0026pagereferer\u003dblank\u0026keyword\u003dnull\u0026clicktype\u003djob","compName":"宁波市金证高科控股有限公司","pubCity":"宁波","pubEx":"1年以上","hasIcon":0,"time":"2016-10-17","liHref":"//job.dajie.com/f7e7e5b3-1e01-43db-bcf9-4ab37f5afc59.html?jobsearch\u003d0\u0026pagereferer\u003dblank\u0026keyword\u003dnull\u0026clicktype\u003dblank","imgSrc":"//fs1.dajie.com/corplogo/50x50.png"},{"jobName":"储备干部6k-8k+免费住宿+提成+五险一金","hasVip":0,"salary":"6000元/月","hasComment":0,"jobHref":"//job.dajie.com/2a71828f-3f26-4baa-bb5a-d1edeecd1439.html?jobsearch\u003d0\u0026pagereferer\u003dblank\u0026keyword\u003dnull\u0026clicktype\u003djob","compName":"宁波景祥环保科技有限公司","pubCity":"宁波","pubEx":"不限","hasIcon":0,"time":"2016-10-17","liHref":"//job.dajie.com/2a71828f-3f26-4baa-bb5a-d1edeecd1439.html?jobsearch\u003d0\u0026pagereferer\u003dblank\u0026keyword\u003dnull\u0026clicktype\u003dblank","imgSrc":"//fs1.dajie.com/corplogo/50x50.png"},{"jobName":"应届毕业生/销售代表4-6K+住宿+五险一金","hasVip":0,"salary":"4000元/月","hasComment":0,"jobHref":"//job.dajie.com/27079eff-a3f1-4a09-ae6f-87b90a77fb28.html?jobsearch\u003d0\u0026pagereferer\u003dblank\u0026keyword\u003dnull\u0026clicktype\u003djob","compName":"宁波景祥环保科技有限公司","pubCity":"宁波","pubEx":"不限","hasIcon":0,"time":"2016-10-17","liHref":"//job.dajie.com/27079eff-a3f1-4a09-ae6f-87b90a77fb28.html?jobsearch\u003d0\u0026pagereferer\u003dblank\u0026keyword\u003dnull\u0026clicktype\u003dblank","imgSrc":"//fs1.dajie.com/corplogo/50x50.png"},{"jobName":"销售代表","pubEdu":"专科","hasVip":0,"salary":"4000元/月","hasComment":0,"jobHref":"//job.dajie.com/a959611a-aae5-4a71-8da6-e2468a13137d.html?jobsearch\u003d0\u0026pagereferer\u003dblank\u0026keyword\u003dnull\u0026clicktype\u003djob","compName":"宁波海睿控股有限公司","pubCity":"宁波","pubEx":"不限","hasIcon":0,"time":"2016-10-17","liHref":"//job.dajie.com/a959611a-aae5-4a71-8da6-e2468a13137d.html?jobsearch\u003d0\u0026pagereferer\u003dblank\u0026keyword\u003dnull\u0026clicktype\u003dblank","imgSrc":"//fs1.dajie.com/corplogo/50x50.png"},{"jobName":"美工","hasVip":0,"salary":"2000元/月","hasComment":0,"jobHref":"//job.dajie.com/fa4992a7-4e47-4bce-b047-0106d850aee9.html?jobsearch\u003d0\u0026pagereferer\u003dblank\u0026keyword\u003dnull\u0026clicktype\u003djob","compName":"宁波小小生活电子商务有限公司","pubCity":"宁波","pubEx":"1年以上","hasIcon":0,"time":"2016-10-17","liHref":"//job.dajie.com/fa4992a7-4e47-4bce-b047-0106d850aee9.html?jobsearch\u003d0\u0026pagereferer\u003dblank\u0026keyword\u003dnull\u0026clicktype\u003dblank","imgSrc":"//fs1.dajie.com/corplogo/50x50.png"},{"jobName":"快消品销售专员4-6k+免费住宿+提成+五险一金","hasVip":0,"salary":"6000元/月","hasComment":0,"jobHref":"//job.dajie.com/fb04972e-b4dc-47e2-b1bd-f64728ed0d28.html?jobsearch\u003d0\u0026pagereferer\u003dblank\u0026keyword\u003dnull\u0026clicktype\u003djob","compName":"宁波景祥环保科技有限公司","pubCity":"宁波","pubEx":"不限","hasIcon":0,"time":"2016-10-17","liHref":"//job.dajie.com/fb04972e-b4dc-47e2-b1bd-f64728ed0d28.html?jobsearch\u003d0\u0026pagereferer\u003dblank\u0026keyword\u003dnull\u0026clicktype\u003dblank","imgSrc":"//fs1.dajie.com/corplogo/50x50.png"},{"jobName":"出纳","pubEdu":"本科","hasVip":0,"salary":"2000元/月","hasComment":0,"jobHref":"//job.dajie.com/20285595-5d18-4c98-8684-c969128feae1.html?jobsearch\u003d0\u0026pagereferer\u003dblank\u0026keyword\u003dnull\u0026clicktype\u003djob","compName":"宁波必琪国际贸易有限公司","pubCity":"宁波","pubEx":"--","hasIcon":0,"time":"2016-10-17","liHref":"//job.dajie.com/20285595-5d18-4c98-8684-c969128feae1.html?jobsearch\u003d0\u0026pagereferer\u003dblank\u0026keyword\u003dnull\u0026clicktype\u003dblank","imgSrc":"//fs1.dajie.com/corplogo/50x50.png"},{"jobName":"诚聘销售精英，月薪6K+（宁波校区）","hasVip":0,"salary":"6000元/月","hasComment":0,"jobHref":"//job.dajie.com/919ce9f3-e1e2-40bd-8708-045938c75b9d.html?jobsearch\u003d0\u0026pagereferer\u003dblank\u0026keyword\u003dnull\u0026clicktype\u003djob","compName":"浙江华博特教育发展有限公司","pubCity":"宁波","pubEx":"不限","hasIcon":0,"time":"2016-10-17","liHref":"//job.dajie.com/919ce9f3-e1e2-40bd-8708-045938c75b9d.html?jobsearch\u003d0\u0026pagereferer\u003dblank\u0026keyword\u003dnull\u0026clicktype\u003dblank","imgSrc":"//fs1.dajie.com/corplogo/50x50.png"}],"salary":"薪资范围","nowPage":168}}