{"result":0,"data":{"total":3821,"city":{"cityName":"宁波","cityId":"330200"},"totalPage":255,"recruitType":"工作类型","keyword":"","list":[{"jobName":"招聘培训专员","hasVip":0,"salary":"面议","hasComment":0,"jobHref":"//job.dajie.com/c85ddb8d-66a9-48bc-b362-a1dadfdb5515.html?jobsearch\u003d0\u0026pagereferer\u003dblank\u0026keyword\u003dnull\u0026clicktype\u003djob","compName":"宁波天真制药有限公司","pubCity":"宁波","pubEx":"不限","hasIcon":0,"time":"2016-10-19","liHref":"//job.dajie.com/c85ddb8d-66a9-48bc-b362-a1dadfdb5515.html?jobsearch\u003d0\u0026pagereferer\u003dblank\u0026keyword\u003dnull\u0026clicktype\u003dblank","imgSrc":"//fs1.dajie.com/corplogo/50x50.png"},{"jobName":"外呼中心客服","pubEdu":"专科","hasVip":0,"salary":"面议","hasComment":0,"jobHref":"//job.dajie.com/c89b558e-398f-4442-966d-394dca6e9334.html?jobsearch\u003d0\u0026pagereferer\u003dblank\u0026keyword\u003dnull\u0026clicktype\u003djob","compName":"浙江盈达科技发展有限公司","pubCity":"宁波","pubEx":"不限","hasIcon":0,"time":"2016-10-19","liHref":"//job.dajie.com/c89b558e-398f-4442-966d-394dca6e9334.html?jobsearch\u003d0\u0026pagereferer\u003dblank\u0026keyword\u003dnull\u0026clicktype\u003dblank","imgSrc":"//fs1.dajie.com/corplogo/50x50.png"},{"jobName":"巡检员","pubEdu":"专科","hasVip":0,"salary":"面议","hasComment":0,"jobHref":"//job.dajie.com/c98064b9-1c4e-44c6-9615-5521a98e6fc5.html?jobsearch\u003d0\u0026pagereferer\u003dblank\u0026keyword\u003dnull\u0026clicktype\u003djob","compName":"宁波余慈物流有限公司","pubCity":"宁波","pubEx":"1年以上","hasIcon":0,"time":"2016-10-19","liHref":"//job.dajie.com/c98064b9-1c4e-44c6-9615-5521a98e6fc5.html?jobsearch\u003d0\u0026pagereferer\u003dblank\u0026keyword\u003dnull\u0026clicktype\u003dblank","imgSrc":"//fs1.dajie.com/corplogo/50x50.png"},{"jobName":"业务员","pubEdu":"专科","hasVip":0,"salary":"面议","hasComment":0,"jobHref":"//job.dajie.com/f14b146a-58a7-4cef-a3a9-433550c6af22.html?jobsearch\u003d0\u0026pagereferer\u003dblank\u0026keyword\u003dnull\u0026clicktype\u003djob","compName":"金光纸业（中国）投资有限公司（APP）","pubCity":"宁波","pubEx":"1年以上","hasIcon":0,"time":"2016-10-19","liHref":"//job.dajie.com/f14b146a-58a7-4cef-a3a9-433550c6af22.html?jobsearch\u003d0\u0026pagereferer\u003dblank\u0026keyword\u003dnull\u0026clicktype\u003dblank","imgSrc":"//fs1.dajie.com/corplogo/50x50.png"},{"jobName":"枫丹店房产销售","hasVip":0,"salary":"6000元/月","hasComment":0,"jobHref":"//job.dajie.com/e3d7bdb4-c66c-4ba9-887b-b9e5f273ae71.html?jobsearch\u003d0\u0026pagereferer\u003dblank\u0026keyword\u003dnull\u0026clicktype\u003djob","compName":"宁波市立得房地产股份有限公司","pubCity":"宁波","pubEx":"不限","hasIcon":0,"time":"2016-10-19","liHref":"//job.dajie.com/e3d7bdb4-c66c-4ba9-887b-b9e5f273ae71.html?jobsearch\u003d0\u0026pagereferer\u003dblank\u0026keyword\u003dnull\u0026clicktype\u003dblank","imgSrc":"//fs1.dajie.com/corplogo/50x50.png"},{"jobName":"中级测试工程师(002547)","hasVip":0,"salary":"面议","hasComment":0,"jobHref":"//job.dajie.com/e7cb2c70-55be-4441-92eb-d4e6d3f55ef1.html?jobsearch\u003d0\u0026pagereferer\u003dblank\u0026keyword\u003dnull\u0026clicktype\u003djob","compName":"敏实集团有限公司","pubCity":"宁波","pubEx":"3年以上","hasIcon":0,"time":"2016-10-19","liHref":"//job.dajie.com/e7cb2c70-55be-4441-92eb-d4e6d3f55ef1.html?jobsearch\u003d0\u0026pagereferer\u003dblank\u0026keyword\u003dnull\u0026clicktype\u003dblank","imgSrc":"//fs1.dajie.com/corplogo/50x50.png"},{"jobName":"资深研发工程师(002542)","hasVip":0,"salary":"面议","hasComment":0,"jobHref":"//job.dajie.com/e967da25-11bc-4533-b8ae-5337036b18eb.html?jobsearch\u003d0\u0026pagereferer\u003dblank\u0026keyword\u003dnull\u0026clicktype\u003djob","compName":"敏实集团有限公司","pubCity":"宁波","pubEx":"5年以上","hasIcon":0,"time":"2016-10-19","liHref":"//job.dajie.com/e967da25-11bc-4533-b8ae-5337036b18eb.html?jobsearch\u003d0\u0026pagereferer\u003dblank\u0026keyword\u003dnull\u0026clicktype\u003dblank","imgSrc":"//fs1.dajie.com/corplogo/50x50.png"},{"jobName":"中级材料工程师(002544)","hasVip":0,"salary":"面议","hasComment":0,"jobHref":"//job.dajie.com/e02a79f5-da3c-4b9d-a816-17e8618dbbd9.html?jobsearch\u003d0\u0026pagereferer\u003dblank\u0026keyword\u003dnull\u0026clicktype\u003djob","compName":"敏实集团有限公司","pubCity":"宁波","pubEx":"3年以上","hasIcon":0,"time":"2016-10-19","liHref":"//job.dajie.com/e02a79f5-da3c-4b9d-a816-17e8618dbbd9.html?jobsearch\u003d0\u0026pagereferer\u003dblank\u0026keyword\u003dnull\u0026clicktype\u003dblank","imgSrc":"//fs1.dajie.com/corplogo/50x50.png"},{"jobName":"人事行政专员","pubEdu":"本科","hasVip":0,"salary":"面议","hasComment":0,"jobHref":"//job.dajie.com/dbdbe134-b104-4b56-85d8-186276a32836.html?jobsearch\u003d0\u0026pagereferer\u003dblank\u0026keyword\u003dnull\u0026clicktype\u003djob","compName":"宁波天真制药有限公司","pubCity":"宁波","pubEx":"1年以上","hasIcon":0,"time":"2016-10-19","liHref":"//job.dajie.com/dbdbe134-b104-4b56-85d8-186276a32836.html?jobsearch\u003d0\u0026pagereferer\u003dblank\u0026keyword\u003dnull\u0026clicktype\u003dblank","imgSrc":"//fs1.dajie.com/corplogo/50x50.png"},{"jobName":"工厂开发业务员","pubEdu":"专科","hasVip":0,"salary":"面议","hasComment":0,"jobHref":"//job.dajie.com/e1fec471-37b0-4194-b7c3-17d81fcc9ed2.html?jobsearch\u003d0\u0026pagereferer\u003dblank\u0026keyword\u003dnull\u0026clicktype\u003djob","compName":"俄罗斯法克托尔责任有限公司宁波代表处","pubCity":"宁波","pubEx":"不限","hasIcon":0,"time":"2016-10-19","liHref":"//job.dajie.com/e1fec471-37b0-4194-b7c3-17d81fcc9ed2.html?jobsearch\u003d0\u0026pagereferer\u003dblank\u0026keyword\u003dnull\u0026clicktype\u003dblank","imgSrc":"//fs1.dajie.com/corplogo/50x50.png"},{"jobName":"产品研发经理(002540)","pubEdu":"本科","hasVip":0,"salary":"面议","hasComment":0,"jobHref":"//job.dajie.com/daf02392-db65-43d9-aefd-97e6f50c6fe2.html?jobsearch\u003d0\u0026pagereferer\u003dblank\u0026keyword\u003dnull\u0026clicktype\u003djob","compName":"敏实集团有限公司","pubCity":"宁波","pubEx":"5年以上","hasIcon":0,"time":"2016-10-19","liHref":"//job.dajie.com/daf02392-db65-43d9-aefd-97e6f50c6fe2.html?jobsearch\u003d0\u0026pagereferer\u003dblank\u0026keyword\u003dnull\u0026clicktype\u003dblank","imgSrc":"//fs1.dajie.com/corplogo/50x50.png"},{"jobName":"樱桃铺经理（宁波）","hasVip":0,"salary":"4000元/月","hasComment":0,"jobHref":"//job.dajie.com/d274cc2c-ca14-4d7c-a6ea-b775378dd0a5.html?jobsearch\u003d0\u0026pagereferer\u003dblank\u0026keyword\u003dnull\u0026clicktype\u003djob","compName":"九樱天下（北京）信息技术有限公司","pubCity":"宁波","pubEx":"不限","hasIcon":0,"time":"2016-10-19","liHref":"//job.dajie.com/d274cc2c-ca14-4d7c-a6ea-b775378dd0a5.html?jobsearch\u003d0\u0026pagereferer\u003dblank\u0026keyword\u003dnull\u0026clicktype\u003dblank","imgSrc":"//fs1.dajie.com/corplogo/50x50.png"},{"jobName":"人事行政专员","pubEdu":"专科","hasVip":0,"salary":"2000元/月","hasComment":0,"jobHref":"//job.dajie.com/d28eefa0-b621-4556-90b3-12b6dfe0a847.html?jobsearch\u003d0\u0026pagereferer\u003dblank\u0026keyword\u003dnull\u0026clicktype\u003djob","compName":"宁波供享农业科技有限公司","pubCity":"宁波","pubEx":"1年以上","hasIcon":0,"time":"2016-10-19","liHref":"//job.dajie.com/d28eefa0-b621-4556-90b3-12b6dfe0a847.html?jobsearch\u003d0\u0026pagereferer\u003dblank\u0026keyword\u003dnull\u0026clicktype\u003dblank","imgSrc":"//fs1.dajie.com/corplogo/50x50.png"},{"jobName":"国企招 Web/HTML5前端开发定岗实习工程师","pubEdu":"专科","hasVip":0,"salary":"4000元/月","hasComment":0,"jobHref":"//job.dajie.com/d7491085-05b5-408d-9166-fb616694a45f.html?jobsearch\u003d0\u0026pagereferer\u003dblank\u0026keyword\u003dnull\u0026clicktype\u003djob","compName":"荣新中关村IT人才服务中心","pubCity":"宁波","pubEx":"不限","hasIcon":0,"time":"2016-10-19","liHref":"//job.dajie.com/d7491085-05b5-408d-9166-fb616694a45f.html?jobsearch\u003d0\u0026pagereferer\u003dblank\u0026keyword\u003dnull\u0026clicktype\u003dblank","imgSrc":"//fs1.dajie.com/corplogo/50x50.png"},{"jobName":"资深材料工程师(002543)","pubEdu":"本科","hasVip":0,"salary":"面议","hasComment":0,"jobHref":"//job.dajie.com/d83340e8-5eac-4fe6-9da3-abb540e7699a.html?jobsearch\u003d0\u0026pagereferer\u003dblank\u0026keyword\u003dnull\u0026clicktype\u003djob","compName":"敏实集团有限公司","pubCity":"宁波","pubEx":"5年以上","hasIcon":0,"time":"2016-10-19","liHref":"//job.dajie.com/d83340e8-5eac-4fe6-9da3-abb540e7699a.html?jobsearch\u003d0\u0026pagereferer\u003dblank\u0026keyword\u003dnull\u0026clicktype\u003dblank","imgSrc":"//fs1.dajie.com/corplogo/50x50.png"}],"salary":"薪资范围","nowPage":138}}