{"result":0,"data":{"total":3821,"city":{"cityName":"宁波","cityId":"330200"},"totalPage":255,"recruitType":"工作类型","keyword":"","list":[{"jobName":"软件工程师","hasVip":0,"salary":"6000元/月","hasComment":0,"jobHref":"//job.dajie.com/4e5578e3-803a-426f-abd0-67f13f588fbf.html?jobsearch\u003d0\u0026pagereferer\u003dblank\u0026keyword\u003dnull\u0026clicktype\u003djob","compName":"宁波互生元机电科技有限公司","pubCity":"宁波","pubEx":"不限","hasIcon":0,"time":"2016-10-13","liHref":"//job.dajie.com/4e5578e3-803a-426f-abd0-67f13f588fbf.html?jobsearch\u003d0\u0026pagereferer\u003dblank\u0026keyword\u003dnull\u0026clicktype\u003dblank","imgSrc":"//fs1.dajie.com/corplogo/50x50.png"},{"jobName":"车间主任","pubEdu":"专科","hasVip":0,"salary":"4000元/月","hasComment":0,"jobHref":"//job.dajie.com/2e18fb60-c44f-4389-a50a-da77e5946f1d.html?jobsearch\u003d0\u0026pagereferer\u003dblank\u0026keyword\u003dnull\u0026clicktype\u003djob","compName":"宁波宜胜照明有限公司","pubCity":"宁波","pubEx":"3年以上","hasIcon":0,"time":"2016-10-13","liHref":"//job.dajie.com/2e18fb60-c44f-4389-a50a-da77e5946f1d.html?jobsearch\u003d0\u0026pagereferer\u003dblank\u0026keyword\u003dnull\u0026clicktype\u003dblank","imgSrc":"//fs1.dajie.com/corplogo/50x50.png"},{"jobName":"业务文员（高提成+双休+住宿）","pubEdu":"专科","hasVip":0,"salary":"4000元/月","hasComment":0,"jobHref":"//job.dajie.com/24ea4a87-f631-47e2-a248-a0e37a246bfb.html?jobsearch\u003d0\u0026pagereferer\u003dblank\u0026keyword\u003dnull\u0026clicktype\u003djob","compName":"浙江鼎盛创世纪投资管理有限公司","pubCity":"宁波","pubEx":"不限","hasIcon":0,"time":"2016-10-13","liHref":"//job.dajie.com/24ea4a87-f631-47e2-a248-a0e37a246bfb.html?jobsearch\u003d0\u0026pagereferer\u003dblank\u0026keyword\u003dnull\u0026clicktype\u003dblank","imgSrc":"//fs1.dajie.com/corplogo/50x50.png"},{"jobName":"餐饮装修公司总经理","hasVip":0,"salary":"面议","hasComment":0,"jobHref":"//job.dajie.com/262eb8ce-00de-453c-a0e9-78487e43513a.html?jobsearch\u003d0\u0026pagereferer\u003dblank\u0026keyword\u003dnull\u0026clicktype\u003djob","compName":"北京华迈管理咨询有限公司","pubCity":"宁波","pubEx":"5年以上","hasIcon":0,"time":"2016-10-13","liHref":"//job.dajie.com/262eb8ce-00de-453c-a0e9-78487e43513a.html?jobsearch\u003d0\u0026pagereferer\u003dblank\u0026keyword\u003dnull\u0026clicktype\u003dblank","imgSrc":"//fs1.dajie.com/corplogo/50x50.png"},{"jobName":"区域销售代表","pubEdu":"专科","hasVip":0,"salary":"10000元/月","hasComment":0,"jobHref":"//job.dajie.com/2702fb27-02e9-4d28-83b9-a3a9af3cf596.html?jobsearch\u003d0\u0026pagereferer\u003dblank\u0026keyword\u003dnull\u0026clicktype\u003djob","compName":"宁波智慧云享教育科技有限公司","pubCity":"宁波","pubEx":"1年以上","hasIcon":0,"time":"2016-10-13","liHref":"//job.dajie.com/2702fb27-02e9-4d28-83b9-a3a9af3cf596.html?jobsearch\u003d0\u0026pagereferer\u003dblank\u0026keyword\u003dnull\u0026clicktype\u003dblank","imgSrc":"//fs1.dajie.com/corplogo/50x50.png"},{"jobName":"平面设计师","pubEdu":"本科","hasVip":0,"salary":"面议","hasComment":0,"jobHref":"//job.dajie.com/25c7f897-8ff3-498e-a045-199ed9c8d8ad.html?jobsearch\u003d0\u0026pagereferer\u003dblank\u0026keyword\u003dnull\u0026clicktype\u003djob","compName":"宁波爱园国际贸易有限公司","pubCity":"宁波","pubEx":"不限","hasIcon":0,"time":"2016-10-13","liHref":"//job.dajie.com/25c7f897-8ff3-498e-a045-199ed9c8d8ad.html?jobsearch\u003d0\u0026pagereferer\u003dblank\u0026keyword\u003dnull\u0026clicktype\u003dblank","imgSrc":"//fs1.dajie.com/corplogo/50x50.png"},{"jobName":"操盘手/交易员","hasVip":0,"salary":"8000元/月","hasComment":0,"jobHref":"//job.dajie.com/35dbf92e-1744-488f-afd2-2f96c2df23f6.html?jobsearch\u003d0\u0026pagereferer\u003dblank\u0026keyword\u003dnull\u0026clicktype\u003djob","compName":"杭州瑞虹金融信息服务有限公司","pubCity":"宁波","pubEx":"不限","hasIcon":0,"time":"2016-10-13","liHref":"//job.dajie.com/35dbf92e-1744-488f-afd2-2f96c2df23f6.html?jobsearch\u003d0\u0026pagereferer\u003dblank\u0026keyword\u003dnull\u0026clicktype\u003dblank","imgSrc":"//fs1.dajie.com/corplogo/50x50.png"},{"jobName":"3000-5000网站编辑/设计师助理/可实习","pubEdu":"专科","hasVip":0,"salary":"4000元/月","hasComment":0,"jobHref":"//job.dajie.com/39c5d8c1-ac7a-42ac-babe-d808ec0f20ed.html?jobsearch\u003d0\u0026pagereferer\u003dblank\u0026keyword\u003dnull\u0026clicktype\u003djob","compName":"中企动力科技股份有限公司","pubCity":"宁波","pubEx":"不限","hasIcon":0,"time":"2016-10-13","liHref":"//job.dajie.com/39c5d8c1-ac7a-42ac-babe-d808ec0f20ed.html?jobsearch\u003d0\u0026pagereferer\u003dblank\u0026keyword\u003dnull\u0026clicktype\u003dblank","imgSrc":"//fs1.dajie.com/corplogo/50x50.png"},{"jobName":"结构工程师","pubEdu":"专科","hasVip":0,"salary":"8000元/月","hasComment":0,"jobHref":"//job.dajie.com/38d1045f-99c1-44e3-8896-3606fc922f8a.html?jobsearch\u003d0\u0026pagereferer\u003dblank\u0026keyword\u003dnull\u0026clicktype\u003djob","compName":"宁波宜胜照明有限公司","pubCity":"宁波","pubEx":"5年以上","hasIcon":0,"time":"2016-10-13","liHref":"//job.dajie.com/38d1045f-99c1-44e3-8896-3606fc922f8a.html?jobsearch\u003d0\u0026pagereferer\u003dblank\u0026keyword\u003dnull\u0026clicktype\u003dblank","imgSrc":"//fs1.dajie.com/corplogo/50x50.png"},{"jobName":"数字电路工程师","hasVip":0,"salary":"面议","hasComment":0,"jobHref":"//job.dajie.com/37cf6bc1-d95e-44d0-9b2e-b939bf6cc619.html?jobsearch\u003d0\u0026pagereferer\u003dblank\u0026keyword\u003dnull\u0026clicktype\u003djob","compName":"宁波互生元机电科技有限公司","pubCity":"宁波","pubEx":"不限","hasIcon":0,"time":"2016-10-13","liHref":"//job.dajie.com/37cf6bc1-d95e-44d0-9b2e-b939bf6cc619.html?jobsearch\u003d0\u0026pagereferer\u003dblank\u0026keyword\u003dnull\u0026clicktype\u003dblank","imgSrc":"//fs1.dajie.com/corplogo/50x50.png"},{"jobName":"BIM桥梁工程师","pubEdu":"本科","hasVip":0,"salary":"4000元/月","hasComment":0,"jobHref":"//job.dajie.com/49ed910e-3b43-44f1-9999-7db226e8d05a.html?jobsearch\u003d0\u0026pagereferer\u003dblank\u0026keyword\u003dnull\u0026clicktype\u003djob","compName":"宁波易比木信息咨询有限公司","pubCity":"宁波","pubEx":"3年以上","hasIcon":0,"time":"2016-10-13","liHref":"//job.dajie.com/49ed910e-3b43-44f1-9999-7db226e8d05a.html?jobsearch\u003d0\u0026pagereferer\u003dblank\u0026keyword\u003dnull\u0026clicktype\u003dblank","imgSrc":"//fs1.dajie.com/corplogo/50x50.png"},{"jobName":"网络客服（高提成+双休+住宿）","pubEdu":"专科","hasVip":0,"salary":"4000元/月","hasComment":0,"jobHref":"//job.dajie.com/53e0af44-abf5-4226-b41c-c12f94f6d24e.html?jobsearch\u003d0\u0026pagereferer\u003dblank\u0026keyword\u003dnull\u0026clicktype\u003djob","compName":"浙江鼎盛创世纪投资管理有限公司","pubCity":"宁波","pubEx":"不限","hasIcon":0,"time":"2016-10-13","liHref":"//job.dajie.com/53e0af44-abf5-4226-b41c-c12f94f6d24e.html?jobsearch\u003d0\u0026pagereferer\u003dblank\u0026keyword\u003dnull\u0026clicktype\u003dblank","imgSrc":"//fs1.dajie.com/corplogo/50x50.png"},{"jobName":"药品质量管理","pubEdu":"本科","hasVip":0,"salary":"4000元/月","hasComment":0,"jobHref":"//job.dajie.com/56ff7652-ce2a-4b40-98ca-5c1230cc4939.html?jobsearch\u003d0\u0026pagereferer\u003dblank\u0026keyword\u003dnull\u0026clicktype\u003djob","compName":"湖南玉新药业有限公司","pubCity":"宁波","pubEx":"1年以上","hasIcon":0,"time":"2016-10-13","liHref":"//job.dajie.com/56ff7652-ce2a-4b40-98ca-5c1230cc4939.html?jobsearch\u003d0\u0026pagereferer\u003dblank\u0026keyword\u003dnull\u0026clicktype\u003dblank","imgSrc":"//fs1.dajie.com/corplogo/50x50.png"},{"jobName":"诚聘原油销售精英底薪4千+提成+双休+社保","pubEdu":"专科","hasVip":0,"salary":"8000元/月","hasComment":0,"jobHref":"//job.dajie.com/a0048c1c-f37f-4f8b-b89b-6a7419ba5f98.html?jobsearch\u003d0\u0026pagereferer\u003dblank\u0026keyword\u003dnull\u0026clicktype\u003djob","compName":"上海甬钰金属有限公司宁波分公司","pubCity":"宁波","pubEx":"不限","hasIcon":0,"time":"2016-10-13","liHref":"//job.dajie.com/a0048c1c-f37f-4f8b-b89b-6a7419ba5f98.html?jobsearch\u003d0\u0026pagereferer\u003dblank\u0026keyword\u003dnull\u0026clicktype\u003dblank","imgSrc":"//fs1.dajie.com/corplogo/50x50.png"},{"jobName":"模拟电路工程师","hasVip":0,"salary":"6000元/月","hasComment":0,"jobHref":"//job.dajie.com/c0d5b7c2-d9c6-4ebd-8606-53ab1debc156.html?jobsearch\u003d0\u0026pagereferer\u003dblank\u0026keyword\u003dnull\u0026clicktype\u003djob","compName":"宁波互生元机电科技有限公司","pubCity":"宁波","pubEx":"不限","hasIcon":0,"time":"2016-10-13","liHref":"//job.dajie.com/c0d5b7c2-d9c6-4ebd-8606-53ab1debc156.html?jobsearch\u003d0\u0026pagereferer\u003dblank\u0026keyword\u003dnull\u0026clicktype\u003dblank","imgSrc":"//fs1.dajie.com/corplogo/50x50.png"}],"salary":"薪资范围","nowPage":227}}