{"result":0,"data":{"total":3821,"city":{"cityName":"宁波","cityId":"330200"},"totalPage":255,"recruitType":"工作类型","keyword":"","list":[{"jobName":"课程顾问/销售/咨询顾问（无责任底薪3500起+提成+奖金）","pubEdu":"专科","hasVip":0,"salary":"8000元/月","hasComment":0,"jobHref":"//job.dajie.com/de62905b-9a5a-47d6-835b-240bc4650389.html?jobsearch\u003d0\u0026pagereferer\u003dblank\u0026keyword\u003dnull\u0026clicktype\u003djob","compName":"宁波市赢在起点教育科技有限公司","pubCity":"宁波","pubEx":"1年以上","hasIcon":0,"time":"2016-10-13","liHref":"//job.dajie.com/de62905b-9a5a-47d6-835b-240bc4650389.html?jobsearch\u003d0\u0026pagereferer\u003dblank\u0026keyword\u003dnull\u0026clicktype\u003dblank","imgSrc":"//fs1.dajie.com/corplogo/50x50.png"},{"jobName":"招商部经理","pubEdu":"专科","hasVip":0,"salary":"6000元/月","hasComment":0,"jobHref":"//job.dajie.com/ddc9f308-6376-4c1a-a6c4-a162cb344afb.html?jobsearch\u003d0\u0026pagereferer\u003dblank\u0026keyword\u003dnull\u0026clicktype\u003djob","compName":"台州神鹰信息咨询服务有限公司","pubCity":"宁波","pubEx":"1年以上","hasIcon":0,"time":"2016-10-13","liHref":"//job.dajie.com/ddc9f308-6376-4c1a-a6c4-a162cb344afb.html?jobsearch\u003d0\u0026pagereferer\u003dblank\u0026keyword\u003dnull\u0026clicktype\u003dblank","imgSrc":"//fs1.dajie.com/corplogo/50x50.png"},{"jobName":"业务员","hasVip":0,"salary":"面议","hasComment":0,"jobHref":"//job.dajie.com/61f630f6-c552-4a1f-86c9-f39bbdedf3b4.html?jobsearch\u003d0\u0026pagereferer\u003dblank\u0026keyword\u003dnull\u0026clicktype\u003djob","compName":"绍兴县富鼎纺织有限公司","pubCity":"宁波","pubEx":"不限","hasIcon":0,"time":"2016-10-13","liHref":"//job.dajie.com/61f630f6-c552-4a1f-86c9-f39bbdedf3b4.html?jobsearch\u003d0\u0026pagereferer\u003dblank\u0026keyword\u003dnull\u0026clicktype\u003dblank","imgSrc":"//fs1.dajie.com/corplogo/50x50.png"},{"jobName":"行政前台","pubEdu":"专科","hasVip":0,"salary":"面议","hasComment":0,"jobHref":"//job.dajie.com/d56a88a2-8c68-4665-942b-568e4ab63dda.html?jobsearch\u003d0\u0026pagereferer\u003dblank\u0026keyword\u003dnull\u0026clicktype\u003djob","compName":"宁波青圃教育投资有限公司","pubCity":"宁波","pubEx":"1年以上","hasIcon":0,"time":"2016-10-13","liHref":"//job.dajie.com/d56a88a2-8c68-4665-942b-568e4ab63dda.html?jobsearch\u003d0\u0026pagereferer\u003dblank\u0026keyword\u003dnull\u0026clicktype\u003dblank","imgSrc":"//fs1.dajie.com/corplogo/50x50.png"},{"jobName":"仓库管理员","hasVip":0,"salary":"2000元/月","hasComment":0,"jobHref":"//job.dajie.com/d80ee74f-310c-4f39-84fa-e45b396f2c65.html?jobsearch\u003d0\u0026pagereferer\u003dblank\u0026keyword\u003dnull\u0026clicktype\u003djob","compName":"宁波威涛电器有限公司","pubCity":"宁波","pubEx":"不限","hasIcon":0,"time":"2016-10-13","liHref":"//job.dajie.com/d80ee74f-310c-4f39-84fa-e45b396f2c65.html?jobsearch\u003d0\u0026pagereferer\u003dblank\u0026keyword\u003dnull\u0026clicktype\u003dblank","imgSrc":"//fs1.dajie.com/corplogo/50x50.png"},{"jobName":"销售主管，经理+免费提供住宿+员工国内外旅游","hasVip":0,"salary":"6000元/月","hasComment":0,"jobHref":"//job.dajie.com/79210364-763f-40ea-ad45-581ce6b52906.html?jobsearch\u003d0\u0026pagereferer\u003dblank\u0026keyword\u003dnull\u0026clicktype\u003djob","compName":"宁波景祥环保科技有限公司","pubCity":"宁波","pubEx":"不限","hasIcon":0,"time":"2016-10-13","liHref":"//job.dajie.com/79210364-763f-40ea-ad45-581ce6b52906.html?jobsearch\u003d0\u0026pagereferer\u003dblank\u0026keyword\u003dnull\u0026clicktype\u003dblank","imgSrc":"//fs1.dajie.com/corplogo/50x50.png"},{"jobName":"早教老师/亲子教师（底薪3000元起+课时费+奖金）","pubEdu":"专科","hasVip":0,"salary":"6000元/月","hasComment":0,"jobHref":"//job.dajie.com/a4e03f27-be2f-4790-aea0-022b0bfcd49a.html?jobsearch\u003d0\u0026pagereferer\u003dblank\u0026keyword\u003dnull\u0026clicktype\u003djob","compName":"宁波市赢在起点教育科技有限公司","pubCity":"宁波","pubEx":"不限","hasIcon":0,"time":"2016-10-13","liHref":"//job.dajie.com/a4e03f27-be2f-4790-aea0-022b0bfcd49a.html?jobsearch\u003d0\u0026pagereferer\u003dblank\u0026keyword\u003dnull\u0026clicktype\u003dblank","imgSrc":"//fs1.dajie.com/corplogo/50x50.png"},{"jobName":"","hasVip":0,"salary":"4000元/月","hasComment":0,"jobHref":"//job.dajie.com/d39363d9-2142-44b4-943e-17cbe04ed97f.html?jobsearch\u003d0\u0026pagereferer\u003dblank\u0026keyword\u003dnull\u0026clicktype\u003djob","compName":"河北顺森贸易有限公司","pubCity":"宁波","pubEx":"不限","hasIcon":0,"time":"2016-10-13","liHref":"//job.dajie.com/d39363d9-2142-44b4-943e-17cbe04ed97f.html?jobsearch\u003d0\u0026pagereferer\u003dblank\u0026keyword\u003dnull\u0026clicktype\u003dblank","imgSrc":"//fs1.dajie.com/corplogo/50x50.png"},{"jobName":"微商专员/微商推广/微商运营","pubEdu":"专科","hasVip":0,"salary":"4000元/月","hasComment":0,"jobHref":"//job.dajie.com/d31b0b63-38c6-4d56-a23c-3b28241d539f.html?jobsearch\u003d0\u0026pagereferer\u003dblank\u0026keyword\u003dnull\u0026clicktype\u003djob","compName":"中健生命科技股份有限公司","pubCity":"宁波","pubEx":"1年以上","hasIcon":0,"time":"2016-10-13","liHref":"//job.dajie.com/d31b0b63-38c6-4d56-a23c-3b28241d539f.html?jobsearch\u003d0\u0026pagereferer\u003dblank\u0026keyword\u003dnull\u0026clicktype\u003dblank","imgSrc":"//fs1.dajie.com/corplogo/50x50.png"},{"jobName":"外派出差/应届生4000-6000+带薪培训+免费住宿","hasVip":0,"salary":"4000元/月","hasComment":0,"jobHref":"//job.dajie.com/6ff1d3ab-7850-4a63-bfa7-5a16cd2eb275.html?jobsearch\u003d0\u0026pagereferer\u003dblank\u0026keyword\u003dnull\u0026clicktype\u003djob","compName":"宁波景祥环保科技有限公司","pubCity":"宁波","pubEx":"不限","hasIcon":0,"time":"2016-10-13","liHref":"//job.dajie.com/6ff1d3ab-7850-4a63-bfa7-5a16cd2eb275.html?jobsearch\u003d0\u0026pagereferer\u003dblank\u0026keyword\u003dnull\u0026clicktype\u003dblank","imgSrc":"//fs1.dajie.com/corplogo/50x50.png"},{"jobName":"储备店长+包住","pubEdu":"专科","hasVip":0,"salary":"4000元/月","hasComment":0,"jobHref":"//job.dajie.com/07a43b46-8fdb-451e-9261-7f17569a5c2e.html?jobsearch\u003d0\u0026pagereferer\u003dblank\u0026keyword\u003dnull\u0026clicktype\u003djob","compName":"宁波海曙量健生物科技有限公司","pubCity":"宁波","pubEx":"不限","hasIcon":0,"time":"2016-10-13","liHref":"//job.dajie.com/07a43b46-8fdb-451e-9261-7f17569a5c2e.html?jobsearch\u003d0\u0026pagereferer\u003dblank\u0026keyword\u003dnull\u0026clicktype\u003dblank","imgSrc":"//fs1.dajie.com/corplogo/50x50.png"},{"jobName":"医院开发人员","pubEdu":"专科","hasVip":0,"salary":"面议","hasComment":0,"jobHref":"//job.dajie.com/08cb4d67-edda-4016-91a0-6580236f83cb.html?jobsearch\u003d0\u0026pagereferer\u003dblank\u0026keyword\u003dnull\u0026clicktype\u003djob","compName":"无锡安之卓医疗机器人有限公司","pubCity":"宁波","pubEx":"3年以上","hasIcon":0,"time":"2016-10-13","liHref":"//job.dajie.com/08cb4d67-edda-4016-91a0-6580236f83cb.html?jobsearch\u003d0\u0026pagereferer\u003dblank\u0026keyword\u003dnull\u0026clicktype\u003dblank","imgSrc":"//fs1.dajie.com/corplogo/50x50.png"},{"jobName":"销售助理（高提成+双休+住宿）","pubEdu":"专科","hasVip":0,"salary":"4000元/月","hasComment":0,"jobHref":"//job.dajie.com/1c7a3b7e-4697-4f7e-9f56-8bbfaa38a333.html?jobsearch\u003d0\u0026pagereferer\u003dblank\u0026keyword\u003dnull\u0026clicktype\u003djob","compName":"浙江鼎盛创世纪投资管理有限公司","pubCity":"宁波","pubEx":"不限","hasIcon":0,"time":"2016-10-13","liHref":"//job.dajie.com/1c7a3b7e-4697-4f7e-9f56-8bbfaa38a333.html?jobsearch\u003d0\u0026pagereferer\u003dblank\u0026keyword\u003dnull\u0026clicktype\u003dblank","imgSrc":"//fs1.dajie.com/corplogo/50x50.png"},{"jobName":"实习生（双休+住宿）","pubEdu":"专科","hasVip":0,"salary":"2000元/月","hasComment":0,"jobHref":"//job.dajie.com/1cbbc9fb-1fd9-4fd8-b5db-1e7195881f90.html?jobsearch\u003d0\u0026pagereferer\u003dblank\u0026keyword\u003dnull\u0026clicktype\u003djob","compName":"浙江鼎盛创世纪投资管理有限公司","pubCity":"宁波","pubEx":"不限","hasIcon":0,"time":"2016-10-13","liHref":"//job.dajie.com/1cbbc9fb-1fd9-4fd8-b5db-1e7195881f90.html?jobsearch\u003d0\u0026pagereferer\u003dblank\u0026keyword\u003dnull\u0026clicktype\u003dblank","imgSrc":"//fs1.dajie.com/corplogo/50x50.png"},{"jobName":"市场拓展总监","pubEdu":"专科","hasVip":0,"salary":"面议","hasComment":0,"jobHref":"//job.dajie.com/33fea7cd-b755-4e7f-8d30-437e34daf752.html?jobsearch\u003d0\u0026pagereferer\u003dblank\u0026keyword\u003dnull\u0026clicktype\u003djob","compName":"宁波暴蜂蜜蚂网络科技有限公司","pubCity":"宁波","pubEx":"5年以上","hasIcon":0,"time":"2016-10-13","liHref":"//job.dajie.com/33fea7cd-b755-4e7f-8d30-437e34daf752.html?jobsearch\u003d0\u0026pagereferer\u003dblank\u0026keyword\u003dnull\u0026clicktype\u003dblank","imgSrc":"//fs1.dajie.com/corplogo/50x50.png"}],"salary":"薪资范围","nowPage":226}}