{"result":0,"data":{"total":7941,"city":{"cityName":"宁波","cityId":"330200"},"totalPage":300,"recruitType":"工作类型","keyword":"","list":[{"jobName":"会计主管","pubEdu":"本科","hasVip":0,"salary":"面议","hasComment":0,"jobHref":"//job.dajie.com/f551305c-8024-4e70-8951-35f8c3d81459.html?jobsearch\u003d0\u0026pagereferer\u003dblank\u0026keyword\u003dnull\u0026clicktype\u003djob","compName":"宁波市甬银企业管理咨询有限公司","pubCity":"宁波","pubEx":"1年以上","hasIcon":0,"time":"1天前","liHref":"//job.dajie.com/f551305c-8024-4e70-8951-35f8c3d81459.html?jobsearch\u003d0\u0026pagereferer\u003dblank\u0026keyword\u003dnull\u0026clicktype\u003dblank","imgSrc":"//fs1.dajie.com/corplogo/50x50.png"},{"jobName":"大丰收餐厅店长","pubEdu":"专科","hasVip":0,"salary":"面议","hasComment":0,"jobHref":"//job.dajie.com/7f361096-62c8-4d0a-a829-3d6aa5124983.html?jobsearch\u003d0\u0026pagereferer\u003dblank\u0026keyword\u003dnull\u0026clicktype\u003djob","compName":"福建省大丰收餐饮有限公司","pubCity":"宁波","pubEx":"1年以上","hasIcon":0,"time":"1天前","liHref":"//job.dajie.com/7f361096-62c8-4d0a-a829-3d6aa5124983.html?jobsearch\u003d0\u0026pagereferer\u003dblank\u0026keyword\u003dnull\u0026clicktype\u003dblank","imgSrc":"//fs1.dajie.com/corplogo/50x50.png"},{"jobName":"工程部经理","pubEdu":"专科","hasVip":0,"salary":"面议","hasComment":0,"jobHref":"//job.dajie.com/65745b11-3fa9-496e-b074-ca1470970a5f.html?jobsearch\u003d0\u0026pagereferer\u003dblank\u0026keyword\u003dnull\u0026clicktype\u003djob","compName":"北京瑞祥佳艺建筑装饰工程有限公司宁波分公司","pubCity":"宁波","pubEx":"5年以上","hasIcon":0,"time":"1天前","liHref":"//job.dajie.com/65745b11-3fa9-496e-b074-ca1470970a5f.html?jobsearch\u003d0\u0026pagereferer\u003dblank\u0026keyword\u003dnull\u0026clicktype\u003dblank","imgSrc":"//fs1.dajie.com/corplogo/50x50.png"},{"jobName":"旅游规划师/策划师","pubEdu":"本科","hasVip":0,"salary":"面议","hasComment":0,"jobHref":"//job.dajie.com/81da2347-b711-44c4-98d2-c9d73f8c5542.html?jobsearch\u003d0\u0026pagereferer\u003dblank\u0026keyword\u003dnull\u0026clicktype\u003djob","compName":"浙江远见旅游设计有限公司","pubCity":"宁波","pubEx":"1年以上","hasIcon":0,"time":"1天前","liHref":"//job.dajie.com/81da2347-b711-44c4-98d2-c9d73f8c5542.html?jobsearch\u003d0\u0026pagereferer\u003dblank\u0026keyword\u003dnull\u0026clicktype\u003dblank","imgSrc":"//fs1.dajie.com/corplogo/50x50.png"},{"jobName":"电工兼保安","hasVip":0,"salary":"面议","hasComment":0,"jobHref":"//job.dajie.com/89a053bf-f676-4522-9827-9c4bd93b682d.html?jobsearch\u003d0\u0026pagereferer\u003dblank\u0026keyword\u003dnull\u0026clicktype\u003djob","compName":"浙江蓝海绿业集团有限公司","pubCity":"宁波","pubEx":"不限","hasIcon":0,"time":"1天前","liHref":"//job.dajie.com/89a053bf-f676-4522-9827-9c4bd93b682d.html?jobsearch\u003d0\u0026pagereferer\u003dblank\u0026keyword\u003dnull\u0026clicktype\u003dblank","imgSrc":"//fs1.dajie.com/corplogo/50x50.png"},{"jobName":"（助理）猎头顾问","pubEdu":"本科","hasVip":0,"salary":"面议","hasComment":0,"jobHref":"//job.dajie.com/6de9707a-6b2a-4d69-9126-c31a79c7aab2.html?jobsearch\u003d0\u0026pagereferer\u003dblank\u0026keyword\u003dnull\u0026clicktype\u003djob","compName":"浙江沃达投资管理有限公司","pubCity":"宁波","pubEx":"1年以上","hasIcon":0,"time":"1天前","liHref":"//job.dajie.com/6de9707a-6b2a-4d69-9126-c31a79c7aab2.html?jobsearch\u003d0\u0026pagereferer\u003dblank\u0026keyword\u003dnull\u0026clicktype\u003dblank","imgSrc":"//fs1.dajie.com/corplogo/50x50.png"},{"jobName":"天猫客服/淘宝客服/网络/在线客服(兼全职)","hasVip":0,"salary":"面议","hasComment":0,"jobHref":"//job.dajie.com/d188e9ea-b603-4c5f-92d0-eb300008661f.html?jobsearch\u003d0\u0026pagereferer\u003dblank\u0026keyword\u003dnull\u0026clicktype\u003djob","compName":"成都家新窗帘有限公司","pubCity":"宁波","pubEx":"不限","hasIcon":0,"time":"1天前","liHref":"//job.dajie.com/d188e9ea-b603-4c5f-92d0-eb300008661f.html?jobsearch\u003d0\u0026pagereferer\u003dblank\u0026keyword\u003dnull\u0026clicktype\u003dblank","imgSrc":"//fs1.dajie.com/corplogo/50x50.png"},{"jobName":"光伏电站运维工程师（杭州湾新区）","pubEdu":"专科","hasVip":0,"salary":"面议","hasComment":0,"jobHref":"//job.dajie.com/339eebf0-c60d-4bec-bd4b-417964d68f76.html?jobsearch\u003d0\u0026pagereferer\u003dblank\u0026keyword\u003dnull\u0026clicktype\u003djob","compName":"施朗德(无锡)电力科技有限责任公司","pubCity":"宁波","pubEx":"不限","hasIcon":0,"time":"1天前","liHref":"//job.dajie.com/339eebf0-c60d-4bec-bd4b-417964d68f76.html?jobsearch\u003d0\u0026pagereferer\u003dblank\u0026keyword\u003dnull\u0026clicktype\u003dblank","imgSrc":"//fs1.dajie.com/corplogo/50x50.png"},{"jobName":"印前主管","pubEdu":"专科","hasVip":0,"salary":"面议","hasComment":0,"jobHref":"//job.dajie.com/6438a8de-03e1-4346-859c-4e00a0b3b71e.html?jobsearch\u003d0\u0026pagereferer\u003dblank\u0026keyword\u003dnull\u0026clicktype\u003djob","compName":"杭州丰源印刷有限公司","pubCity":"宁波","pubEx":"不限","hasIcon":0,"time":"1天前","liHref":"//job.dajie.com/6438a8de-03e1-4346-859c-4e00a0b3b71e.html?jobsearch\u003d0\u0026pagereferer\u003dblank\u0026keyword\u003dnull\u0026clicktype\u003dblank","imgSrc":"//fs1.dajie.com/corplogo/50x50.png"},{"jobName":"中国插花艺术馆前台接待员/讲解员","pubEdu":"专科","hasVip":0,"salary":"面议","hasComment":0,"jobHref":"//job.dajie.com/b97365dd-ddbc-4cd7-88c0-6e88ddc723e9.html?jobsearch\u003d0\u0026pagereferer\u003dblank\u0026keyword\u003dnull\u0026clicktype\u003djob","compName":"浙江蓝海绿业集团有限公司","pubCity":"宁波","pubEx":"1年以上","hasIcon":0,"time":"1天前","liHref":"//job.dajie.com/b97365dd-ddbc-4cd7-88c0-6e88ddc723e9.html?jobsearch\u003d0\u0026pagereferer\u003dblank\u0026keyword\u003dnull\u0026clicktype\u003dblank","imgSrc":"//fs1.dajie.com/corplogo/50x50.png"},{"jobName":"平面设计师，网页设计师（高薪+职业规划）","hasVip":0,"salary":"面议","hasComment":0,"jobHref":"//job.dajie.com/1a64bc1f-98f9-41b1-9e71-08826b80ce84.html?jobsearch\u003d0\u0026pagereferer\u003dblank\u0026keyword\u003dnull\u0026clicktype\u003djob","compName":"宁波铮程制冷空调有限公司","pubCity":"宁波","pubEx":"不限","hasIcon":0,"time":"1天前","liHref":"//job.dajie.com/1a64bc1f-98f9-41b1-9e71-08826b80ce84.html?jobsearch\u003d0\u0026pagereferer\u003dblank\u0026keyword\u003dnull\u0026clicktype\u003dblank","imgSrc":"//fs1.dajie.com/corplogo/50x50.png"},{"jobName":"市场督导 促销员","hasVip":0,"salary":"面议","hasComment":0,"jobHref":"//job.dajie.com/a21db02f-49ce-4462-ae77-816b6a5da303.html?jobsearch\u003d0\u0026pagereferer\u003dblank\u0026keyword\u003dnull\u0026clicktype\u003djob","compName":"南京世具文化传播有限公司","pubCity":"宁波","pubEx":"不限","hasIcon":0,"time":"1天前","liHref":"//job.dajie.com/a21db02f-49ce-4462-ae77-816b6a5da303.html?jobsearch\u003d0\u0026pagereferer\u003dblank\u0026keyword\u003dnull\u0026clicktype\u003dblank","imgSrc":"//fs1.dajie.com/corplogo/50x50.png"},{"jobName":"培训助理","pubEdu":"专科","hasVip":0,"salary":"面议","hasComment":0,"jobHref":"//job.dajie.com/8e535810-d5ff-456d-8ebf-dd61cd673f5c.html?jobsearch\u003d0\u0026pagereferer\u003dblank\u0026keyword\u003dnull\u0026clicktype\u003djob","compName":"浙江蓝海绿业集团有限公司","pubCity":"宁波","pubEx":"1年以上","hasIcon":0,"time":"1天前","liHref":"//job.dajie.com/8e535810-d5ff-456d-8ebf-dd61cd673f5c.html?jobsearch\u003d0\u0026pagereferer\u003dblank\u0026keyword\u003dnull\u0026clicktype\u003dblank","imgSrc":"//fs1.dajie.com/corplogo/50x50.png"},{"jobName":"资深业务员","pubEdu":"专科","hasVip":0,"salary":"面议","hasComment":0,"jobHref":"//job.dajie.com/136347e3-e357-4af2-b9d1-e9eee2d87960.html?jobsearch\u003d0\u0026pagereferer\u003dblank\u0026keyword\u003dnull\u0026clicktype\u003djob","compName":"宁波高新区伊家宜家居用品有限公司","pubCity":"宁波","pubEx":"3年以上","hasIcon":0,"time":"1天前","liHref":"//job.dajie.com/136347e3-e357-4af2-b9d1-e9eee2d87960.html?jobsearch\u003d0\u0026pagereferer\u003dblank\u0026keyword\u003dnull\u0026clicktype\u003dblank","imgSrc":"//fs1.dajie.com/corplogo/50x50.png"},{"jobName":"业务员（90后公司）","pubEdu":"专科","hasVip":0,"salary":"面议","hasComment":0,"jobHref":"//job.dajie.com/09117c20-76ff-48db-8e13-67fb2a137b0c.html?jobsearch\u003d0\u0026pagereferer\u003dblank\u0026keyword\u003dnull\u0026clicktype\u003djob","compName":"宁波八方鸿运装饰工程有限公司","pubCity":"宁波","pubEx":"1年以上","hasIcon":0,"time":"1天前","liHref":"//job.dajie.com/09117c20-76ff-48db-8e13-67fb2a137b0c.html?jobsearch\u003d0\u0026pagereferer\u003dblank\u0026keyword\u003dnull\u0026clicktype\u003dblank","imgSrc":"//fs1.dajie.com/corplogo/50x50.png"}],"salary":"薪资范围","nowPage":73}}