{"result":0,"data":{"total":7941,"city":{"cityName":"宁波","cityId":"330200"},"totalPage":300,"recruitType":"工作类型","keyword":"","list":[{"jobName":"食堂厨师","hasVip":0,"salary":"面议","hasComment":0,"jobHref":"//job.dajie.com/45f58f93-5e82-496c-886f-9a458b59d860.html?jobsearch\u003d0\u0026pagereferer\u003dblank\u0026keyword\u003dnull\u0026clicktype\u003djob","compName":"宁波普瑞柏生物技术股份有限公司","pubCity":"宁波","pubEx":"1年以上","hasIcon":0,"time":"2016-11-13","liHref":"//job.dajie.com/45f58f93-5e82-496c-886f-9a458b59d860.html?jobsearch\u003d0\u0026pagereferer\u003dblank\u0026keyword\u003dnull\u0026clicktype\u003dblank","imgSrc":"//fs1.dajie.com/corplogo/50x50.png"},{"jobName":"消防工程师","pubEdu":"专科","hasVip":0,"salary":"面议","hasComment":0,"jobHref":"//job.dajie.com/73391fa4-194a-4884-ab08-1a4cb744de59.html?jobsearch\u003d0\u0026pagereferer\u003dblank\u0026keyword\u003dnull\u0026clicktype\u003djob","compName":"万科物业","pubCity":"宁波","pubEx":"1年以上","hasIcon":0,"time":"2016-11-13","liHref":"//job.dajie.com/73391fa4-194a-4884-ab08-1a4cb744de59.html?jobsearch\u003d0\u0026pagereferer\u003dblank\u0026keyword\u003dnull\u0026clicktype\u003dblank","imgSrc":"//fs1.dajie.com/corplogo/50x50.png"},{"jobName":"高薪诚聘初中数学教师+五险一金","pubEdu":"本科","hasVip":0,"salary":"面议","hasComment":0,"jobHref":"//job.dajie.com/f897c5d1-266a-40f6-ab43-5b72c7b5729b.html?jobsearch\u003d0\u0026pagereferer\u003dblank\u0026keyword\u003dnull\u0026clicktype\u003djob","compName":"宁波市海曙区精锐智汇教育培训学校","pubCity":"宁波","pubEx":"不限","hasIcon":0,"time":"2016-11-13","liHref":"//job.dajie.com/f897c5d1-266a-40f6-ab43-5b72c7b5729b.html?jobsearch\u003d0\u0026pagereferer\u003dblank\u0026keyword\u003dnull\u0026clicktype\u003dblank","imgSrc":"//fs1.dajie.com/corplogo/50x50.png"},{"jobName":"会计","pubEdu":"专科","hasVip":0,"salary":"面议","hasComment":0,"jobHref":"//job.dajie.com/7385963b-4938-4bbc-a25e-0a0258cf59de.html?jobsearch\u003d0\u0026pagereferer\u003dblank\u0026keyword\u003dnull\u0026clicktype\u003djob","compName":"宁波先锋新材料股份有限公司","pubCity":"宁波","pubEx":"1年以上","hasIcon":0,"time":"2016-11-13","liHref":"//job.dajie.com/7385963b-4938-4bbc-a25e-0a0258cf59de.html?jobsearch\u003d0\u0026pagereferer\u003dblank\u0026keyword\u003dnull\u0026clicktype\u003dblank","imgSrc":"//fs1.dajie.com/corplogo/50x50.png"},{"jobName":"办公室文员【底薪4500+接受应届生】五险一金、两人间住宿","pubEdu":"专科","hasVip":0,"salary":"面议","hasComment":0,"jobHref":"//job.dajie.com/3342b68a-0a32-4a69-9caf-c50b7c06ccdd.html?jobsearch\u003d0\u0026pagereferer\u003dblank\u0026keyword\u003dnull\u0026clicktype\u003djob","compName":"上海朝勇投资有限公司","pubCity":"宁波","pubEx":"不限","hasIcon":0,"time":"2016-11-13","liHref":"//job.dajie.com/3342b68a-0a32-4a69-9caf-c50b7c06ccdd.html?jobsearch\u003d0\u0026pagereferer\u003dblank\u0026keyword\u003dnull\u0026clicktype\u003dblank","imgSrc":"//fs1.dajie.com/corplogo/50x50.png"},{"jobName":"储备干部（带薪培训+双休+住宿）","pubEdu":"专科","hasVip":0,"salary":"面议","hasComment":0,"jobHref":"//job.dajie.com/47e9b9a6-5928-489e-80ea-ac363b9c6e4e.html?jobsearch\u003d0\u0026pagereferer\u003dblank\u0026keyword\u003dnull\u0026clicktype\u003djob","compName":"浙江鼎盛创世纪投资管理有限公司","pubCity":"宁波","pubEx":"不限","hasIcon":0,"time":"2016-11-13","liHref":"//job.dajie.com/47e9b9a6-5928-489e-80ea-ac363b9c6e4e.html?jobsearch\u003d0\u0026pagereferer\u003dblank\u0026keyword\u003dnull\u0026clicktype\u003dblank","imgSrc":"//fs1.dajie.com/corplogo/50x50.png"},{"jobName":"【实时结算】手机APP试玩全/兼职【苹果、安卓皆可在家工作】","hasVip":0,"salary":"面议","hasComment":0,"jobHref":"//job.dajie.com/58fce1c6-8c66-49d9-a87d-7e8f0f2fd4b9.html?jobsearch\u003d0\u0026pagereferer\u003dblank\u0026keyword\u003dnull\u0026clicktype\u003djob","compName":"北京大福融通智能科技有限公司","pubCity":"宁波","pubEx":"不限","hasIcon":0,"time":"2016-11-13","liHref":"//job.dajie.com/58fce1c6-8c66-49d9-a87d-7e8f0f2fd4b9.html?jobsearch\u003d0\u0026pagereferer\u003dblank\u0026keyword\u003dnull\u0026clicktype\u003dblank","imgSrc":"//fs1.dajie.com/corplogo/50x50.png"},{"jobName":"诚聘一名招聘专员，双休+五险","hasVip":0,"salary":"面议","hasComment":0,"jobHref":"//job.dajie.com/018dfbae-20f2-4c74-9623-6b4c79c7f092.html?jobsearch\u003d0\u0026pagereferer\u003dblank\u0026keyword\u003dnull\u0026clicktype\u003djob","compName":"宁波穗元商品经营有限公司","pubCity":"宁波","pubEx":"不限","hasIcon":0,"time":"2016-11-13","liHref":"//job.dajie.com/018dfbae-20f2-4c74-9623-6b4c79c7f092.html?jobsearch\u003d0\u0026pagereferer\u003dblank\u0026keyword\u003dnull\u0026clicktype\u003dblank","imgSrc":"//fs1.dajie.com/corplogo/50x50.png"},{"jobName":"业务助理","hasVip":0,"salary":"面议","hasComment":0,"jobHref":"//job.dajie.com/136fd73e-5e81-4f53-be74-d798ffeeda3a.html?jobsearch\u003d0\u0026pagereferer\u003dblank\u0026keyword\u003dnull\u0026clicktype\u003djob","compName":"宁波迅迪企业管理咨询有限公司","pubCity":"宁波","pubEx":"不限","hasIcon":0,"time":"2016-11-13","liHref":"//job.dajie.com/136fd73e-5e81-4f53-be74-d798ffeeda3a.html?jobsearch\u003d0\u0026pagereferer\u003dblank\u0026keyword\u003dnull\u0026clicktype\u003dblank","imgSrc":"//fs1.dajie.com/corplogo/50x50.png"},{"jobName":"5K急招","hasVip":0,"salary":"面议","hasComment":0,"jobHref":"//job.dajie.com/8e02427c-e716-40d8-8300-536f6f27bfa2.html?jobsearch\u003d0\u0026pagereferer\u003dblank\u0026keyword\u003dnull\u0026clicktype\u003djob","compName":"宁波七寸网络科技有限公司","pubCity":"宁波","pubEx":"不限","hasIcon":0,"time":"2016-11-13","liHref":"//job.dajie.com/8e02427c-e716-40d8-8300-536f6f27bfa2.html?jobsearch\u003d0\u0026pagereferer\u003dblank\u0026keyword\u003dnull\u0026clicktype\u003dblank","imgSrc":"//fs1.dajie.com/corplogo/50x50.png"},{"jobName":"高级客户经理","pubEdu":"本科","hasVip":0,"salary":"面议","hasComment":0,"jobHref":"//job.dajie.com/b01a8544-d640-4b5e-8b2d-4eef088a0156.html?jobsearch\u003d0\u0026pagereferer\u003dblank\u0026keyword\u003dnull\u0026clicktype\u003djob","compName":"永安期货股份有限公司","pubCity":"宁波","pubEx":"不限","hasIcon":0,"time":"2016-11-13","liHref":"//job.dajie.com/b01a8544-d640-4b5e-8b2d-4eef088a0156.html?jobsearch\u003d0\u0026pagereferer\u003dblank\u0026keyword\u003dnull\u0026clicktype\u003dblank","imgSrc":"//fs1.dajie.com/corplogo/50x50.png"},{"jobName":"17届实习生（理工科类优先+专业培训+长远发展）","pubEdu":"本科","hasVip":0,"salary":"面议","hasComment":0,"jobHref":"//job.dajie.com/4becfe4b-5907-4761-90de-c4f63ec2f731.html?jobsearch\u003d0\u0026pagereferer\u003dblank\u0026keyword\u003dnull\u0026clicktype\u003djob","compName":"宁波维正知识产权代理有限公司","pubCity":"宁波","pubEx":"不限","hasIcon":0,"time":"2016-11-13","liHref":"//job.dajie.com/4becfe4b-5907-4761-90de-c4f63ec2f731.html?jobsearch\u003d0\u0026pagereferer\u003dblank\u0026keyword\u003dnull\u0026clicktype\u003dblank","imgSrc":"//fs1.dajie.com/corplogo/50x50.png"},{"jobName":"高薪诚聘初中科学教师+五险一金","pubEdu":"本科","hasVip":0,"salary":"面议","hasComment":0,"jobHref":"//job.dajie.com/7f65c2c3-8e1d-4459-a9e3-9871dbe736bb.html?jobsearch\u003d0\u0026pagereferer\u003dblank\u0026keyword\u003dnull\u0026clicktype\u003djob","compName":"宁波市海曙区精锐智汇教育培训学校","pubCity":"宁波","pubEx":"不限","hasIcon":0,"time":"2016-11-13","liHref":"//job.dajie.com/7f65c2c3-8e1d-4459-a9e3-9871dbe736bb.html?jobsearch\u003d0\u0026pagereferer\u003dblank\u0026keyword\u003dnull\u0026clicktype\u003dblank","imgSrc":"//fs1.dajie.com/corplogo/50x50.png"},{"jobName":"仓库主管","pubEdu":"专科","hasVip":0,"salary":"面议","hasComment":0,"jobHref":"//job.dajie.com/fa993bc4-b162-4ec5-9b4d-d19d30b0ce54.html?jobsearch\u003d0\u0026pagereferer\u003dblank\u0026keyword\u003dnull\u0026clicktype\u003djob","compName":"慈溪市诚佳五金工具有限公司","pubCity":"宁波","pubEx":"3年以上","hasIcon":0,"time":"2016-11-13","liHref":"//job.dajie.com/fa993bc4-b162-4ec5-9b4d-d19d30b0ce54.html?jobsearch\u003d0\u0026pagereferer\u003dblank\u0026keyword\u003dnull\u0026clicktype\u003dblank","imgSrc":"//fs1.dajie.com/corplogo/50x50.png"},{"jobName":"兼职淘宝客服","hasVip":0,"salary":"面议","hasComment":0,"jobHref":"//job.dajie.com/6f195b41-a96d-44ed-a86c-ab3aa8209747.html?jobsearch\u003d0\u0026pagereferer\u003dblank\u0026keyword\u003dnull\u0026clicktype\u003djob","compName":"浙江黄古林床上用品有限公司","pubCity":"宁波","pubEx":"不限","hasIcon":0,"time":"2016-11-13","liHref":"//job.dajie.com/6f195b41-a96d-44ed-a86c-ab3aa8209747.html?jobsearch\u003d0\u0026pagereferer\u003dblank\u0026keyword\u003dnull\u0026clicktype\u003dblank","imgSrc":"//fs1.dajie.com/corplogo/50x50.png"}],"salary":"薪资范围","nowPage":293}}