{"result":0,"data":{"total":7941,"city":{"cityName":"宁波","cityId":"330200"},"totalPage":300,"recruitType":"工作类型","keyword":"","list":[{"jobName":"实习生（双休+住宿）","pubEdu":"专科","hasVip":0,"salary":"面议","hasComment":0,"jobHref":"//job.dajie.com/badedf23-aeb9-4c8d-8431-188436cd820b.html?jobsearch\u003d0\u0026pagereferer\u003dblank\u0026keyword\u003dnull\u0026clicktype\u003djob","compName":"浙江鼎盛创世纪投资管理有限公司","pubCity":"宁波","pubEx":"不限","hasIcon":0,"time":"2016-11-13","liHref":"//job.dajie.com/badedf23-aeb9-4c8d-8431-188436cd820b.html?jobsearch\u003d0\u0026pagereferer\u003dblank\u0026keyword\u003dnull\u0026clicktype\u003dblank","imgSrc":"//fs1.dajie.com/corplogo/50x50.png"},{"jobName":"（发动机）运动系统设计工程师","hasVip":0,"salary":"面议","hasComment":0,"jobHref":"//job.dajie.com/7c06d8ec-f787-4eae-b679-6eaeaa8e87a1.html?jobsearch\u003d0\u0026pagereferer\u003dblank\u0026keyword\u003dnull\u0026clicktype\u003djob","compName":"宁波市鄞州德来特技术有限公司","pubCity":"宁波","pubEx":"不限","hasIcon":0,"time":"2016-11-13","liHref":"//job.dajie.com/7c06d8ec-f787-4eae-b679-6eaeaa8e87a1.html?jobsearch\u003d0\u0026pagereferer\u003dblank\u0026keyword\u003dnull\u0026clicktype\u003dblank","imgSrc":"//fs1.dajie.com/corplogo/50x50.png"},{"jobName":"211+985管培生","pubEdu":"本科","hasVip":0,"salary":"面议","hasComment":0,"jobHref":"//job.dajie.com/d1520659-ffa9-482b-a7c0-42c5e1d6b67a.html?jobsearch\u003d0\u0026pagereferer\u003dblank\u0026keyword\u003dnull\u0026clicktype\u003djob","compName":"宁波维正知识产权代理有限公司","pubCity":"宁波","pubEx":"不限","hasIcon":0,"time":"2016-11-13","liHref":"//job.dajie.com/d1520659-ffa9-482b-a7c0-42c5e1d6b67a.html?jobsearch\u003d0\u0026pagereferer\u003dblank\u0026keyword\u003dnull\u0026clicktype\u003dblank","imgSrc":"//fs1.dajie.com/corplogo/50x50.png"},{"jobName":"水利、计算机、广告策划、平面设计","pubEdu":"本科","hasVip":0,"salary":"面议","hasComment":0,"jobHref":"//job.dajie.com/b070455f-ed46-4187-ba19-0961a5d89be5.html?jobsearch\u003d0\u0026pagereferer\u003dblank\u0026keyword\u003dnull\u0026clicktype\u003djob","compName":"宁波弘泰水利信息科技有限公司","pubCity":"宁波","pubEx":"不限","hasIcon":0,"time":"2016-11-13","liHref":"//job.dajie.com/b070455f-ed46-4187-ba19-0961a5d89be5.html?jobsearch\u003d0\u0026pagereferer\u003dblank\u0026keyword\u003dnull\u0026clicktype\u003dblank","imgSrc":"//fs1.dajie.com/corplogo/50x50.png"},{"jobName":"【名企新起点】猎头助理顾问（五险一金+丰厚待遇+季度晋升）","pubEdu":"本科","hasVip":0,"salary":"面议","hasComment":0,"jobHref":"//job.dajie.com/4a5d39c7-3ae0-423c-8cd8-6cb5a0e92f0b.html?jobsearch\u003d0\u0026pagereferer\u003dblank\u0026keyword\u003dnull\u0026clicktype\u003djob","compName":"上海埃摩森企业管理咨询有限公司","pubCity":"宁波","pubEx":"不限","hasIcon":0,"time":"2016-11-13","liHref":"//job.dajie.com/4a5d39c7-3ae0-423c-8cd8-6cb5a0e92f0b.html?jobsearch\u003d0\u0026pagereferer\u003dblank\u0026keyword\u003dnull\u0026clicktype\u003dblank","imgSrc":"//fs1.dajie.com/corplogo/50x50.png"},{"jobName":"高薪诚聘招生/教育顾问","pubEdu":"专科","hasVip":0,"salary":"面议","hasComment":0,"jobHref":"//job.dajie.com/bafd1e64-8d81-40b4-aac1-3c0317fe77c7.html?jobsearch\u003d0\u0026pagereferer\u003dblank\u0026keyword\u003dnull\u0026clicktype\u003djob","compName":"宁波市海曙区精锐智汇教育培训学校","pubCity":"宁波","pubEx":"不限","hasIcon":0,"time":"2016-11-13","liHref":"//job.dajie.com/bafd1e64-8d81-40b4-aac1-3c0317fe77c7.html?jobsearch\u003d0\u0026pagereferer\u003dblank\u0026keyword\u003dnull\u0026clicktype\u003dblank","imgSrc":"//fs1.dajie.com/corplogo/50x50.png"},{"jobName":"商标转让经纪人","hasVip":0,"salary":"面议","hasComment":0,"jobHref":"//job.dajie.com/10d346b3-d6e6-4897-99df-5df94e2120ed.html?jobsearch\u003d0\u0026pagereferer\u003dblank\u0026keyword\u003dnull\u0026clicktype\u003djob","compName":"浙江金牌商标代理有限公司","pubCity":"宁波","pubEx":"1年以上","hasIcon":0,"time":"2016-11-13","liHref":"//job.dajie.com/10d346b3-d6e6-4897-99df-5df94e2120ed.html?jobsearch\u003d0\u0026pagereferer\u003dblank\u0026keyword\u003dnull\u0026clicktype\u003dblank","imgSrc":"//fs1.dajie.com/corplogo/50x50.png"},{"jobName":"急聘微信运营专员","pubEdu":"专科","hasVip":0,"salary":"面议","hasComment":0,"jobHref":"//job.dajie.com/b6e308c4-ee45-4cd7-bc90-e4b60b01bfbb.html?jobsearch\u003d0\u0026pagereferer\u003dblank\u0026keyword\u003dnull\u0026clicktype\u003djob","compName":"卡说信息技术有限公司","pubCity":"宁波","pubEx":"1年以上","hasIcon":0,"time":"2016-11-13","liHref":"//job.dajie.com/b6e308c4-ee45-4cd7-bc90-e4b60b01bfbb.html?jobsearch\u003d0\u0026pagereferer\u003dblank\u0026keyword\u003dnull\u0026clicktype\u003dblank","imgSrc":"//fs1.dajie.com/corplogo/50x50.png"},{"jobName":"培训师","hasVip":0,"salary":"面议","hasComment":0,"jobHref":"//job.dajie.com/d0842fa7-5d78-42ff-b84e-318af99a546b.html?jobsearch\u003d0\u0026pagereferer\u003dblank\u0026keyword\u003dnull\u0026clicktype\u003djob","compName":"宁波聪聪教育科技有限公司","pubCity":"宁波","pubEx":"不限","hasIcon":0,"time":"2016-11-13","liHref":"//job.dajie.com/d0842fa7-5d78-42ff-b84e-318af99a546b.html?jobsearch\u003d0\u0026pagereferer\u003dblank\u0026keyword\u003dnull\u0026clicktype\u003dblank","imgSrc":"//fs1.dajie.com/corplogo/50x50.png"},{"jobName":"外贸采购助理（化工）","pubEdu":"本科","hasVip":0,"salary":"面议","hasComment":0,"jobHref":"//job.dajie.com/851aa0af-0e09-496d-b3f6-2f7705c9c3a2.html?jobsearch\u003d0\u0026pagereferer\u003dblank\u0026keyword\u003dnull\u0026clicktype\u003djob","compName":"宁波莫斯化工有限公司","pubCity":"宁波","pubEx":"1年以上","hasIcon":0,"time":"2016-11-13","liHref":"//job.dajie.com/851aa0af-0e09-496d-b3f6-2f7705c9c3a2.html?jobsearch\u003d0\u0026pagereferer\u003dblank\u0026keyword\u003dnull\u0026clicktype\u003dblank","imgSrc":"//fs1.dajie.com/corplogo/50x50.png"},{"jobName":"高级VC++软件工程师（浙江、广东）","pubEdu":"本科","hasVip":0,"salary":"面议","hasComment":0,"jobHref":"//job.dajie.com/0405b1e1-29dd-4bb4-9e30-7d10b8f05829.html?jobsearch\u003d0\u0026pagereferer\u003dblank\u0026keyword\u003dnull\u0026clicktype\u003djob","compName":"华北计算技术研究所","pubCity":"宁波","pubEx":"3年以上","hasIcon":0,"time":"2016-11-13","liHref":"//job.dajie.com/0405b1e1-29dd-4bb4-9e30-7d10b8f05829.html?jobsearch\u003d0\u0026pagereferer\u003dblank\u0026keyword\u003dnull\u0026clicktype\u003dblank","imgSrc":"//fs1.dajie.com/corplogo/50x50.png"},{"jobName":"智能化弱电工程师","pubEdu":"专科","hasVip":0,"salary":"面议","hasComment":0,"jobHref":"//job.dajie.com/6ab7b937-094e-4d87-a42c-d73a4dc5c184.html?jobsearch\u003d0\u0026pagereferer\u003dblank\u0026keyword\u003dnull\u0026clicktype\u003djob","compName":"万科物业","pubCity":"宁波","pubEx":"1年以上","hasIcon":0,"time":"2016-11-13","liHref":"//job.dajie.com/6ab7b937-094e-4d87-a42c-d73a4dc5c184.html?jobsearch\u003d0\u0026pagereferer\u003dblank\u0026keyword\u003dnull\u0026clicktype\u003dblank","imgSrc":"//fs1.dajie.com/corplogo/50x50.png"},{"jobName":"高薪诚聘设计学徒可应届待遇从优","hasVip":0,"salary":"面议","hasComment":0,"jobHref":"//job.dajie.com/919ea8b2-f222-461c-9aa8-6f8f1727dbfe.html?jobsearch\u003d0\u0026pagereferer\u003dblank\u0026keyword\u003dnull\u0026clicktype\u003djob","compName":"宁波七寸网络科技有限公司","pubCity":"宁波","pubEx":"不限","hasIcon":0,"time":"2016-11-13","liHref":"//job.dajie.com/919ea8b2-f222-461c-9aa8-6f8f1727dbfe.html?jobsearch\u003d0\u0026pagereferer\u003dblank\u0026keyword\u003dnull\u0026clicktype\u003dblank","imgSrc":"//fs1.dajie.com/corplogo/50x50.png"},{"jobName":"销售代表","hasVip":0,"salary":"面议","hasComment":0,"jobHref":"//job.dajie.com/d36caf73-2981-46e5-a962-5a97eb8714d1.html?jobsearch\u003d0\u0026pagereferer\u003dblank\u0026keyword\u003dnull\u0026clicktype\u003djob","compName":"杭州显俊教育科技有限公司","pubCity":"宁波","pubEx":"不限","hasIcon":0,"time":"2016-11-13","liHref":"//job.dajie.com/d36caf73-2981-46e5-a962-5a97eb8714d1.html?jobsearch\u003d0\u0026pagereferer\u003dblank\u0026keyword\u003dnull\u0026clicktype\u003dblank","imgSrc":"//fs1.dajie.com/corplogo/50x50.png"},{"jobName":"银行风险管理","pubEdu":"本科","hasVip":0,"salary":"面议","hasComment":0,"jobHref":"//job.dajie.com/599930d7-ef2b-45a1-bcf5-d28810433f65.html?jobsearch\u003d0\u0026pagereferer\u003dblank\u0026keyword\u003dnull\u0026clicktype\u003djob","compName":"歌途网络科技有限公司","pubCity":"宁波","pubEx":"不限","hasIcon":0,"time":"2016-11-13","liHref":"//job.dajie.com/599930d7-ef2b-45a1-bcf5-d28810433f65.html?jobsearch\u003d0\u0026pagereferer\u003dblank\u0026keyword\u003dnull\u0026clicktype\u003dblank","imgSrc":"//fs1.dajie.com/corplogo/50x50.png"}],"salary":"薪资范围","nowPage":294}}