{"result":0,"data":{"total":7941,"city":{"cityName":"宁波","cityId":"330200"},"totalPage":300,"recruitType":"工作类型","keyword":"","list":[{"jobName":"售后技术专员","logoHref":"//www.dajie.com/corp/6009888?clicktype\u003dlogo\u0026jobsearch\u003d0\u0026pagereferer\u003dblank\u0026keyword\u003dnull","pubEdu":"专科","hasVip":0,"pubComp":"主管 • 杨先生","salary":"3000-5000元/月","hasComment":0,"jobHref":"//job.dajie.com/ab440627-8fb4-43f1-9380-80a3aabd277f.html?jobsearch\u003d0\u0026pagereferer\u003dblank\u0026keyword\u003dnull\u0026clicktype\u003djob","compName":"宁波德业日用电器科技有限公司","pubCity":"宁波","compHref":"//www.dajie.com/corp/6009888?clicktype\u003dname\u0026jobsearch\u003d0\u0026pagereferer\u003dblank\u0026keyword\u003dnull","pubEx":"不限","hasIcon":0,"time":"2016-10-12","liHref":"//job.dajie.com/ab440627-8fb4-43f1-9380-80a3aabd277f.html?jobsearch\u003d0\u0026pagereferer\u003dblank\u0026keyword\u003dnull\u0026clicktype\u003dblank","imgSrc":"//fs1.dajie.com/corplogo/50x50.png"},{"jobName":"团险部-人管业管岗","logoHref":"//sinosig.dajie.com?clicktype\u003dlogo\u0026jobsearch\u003d0\u0026pagereferer\u003dblank\u0026keyword\u003dnull","levelRate":94.0,"pubEdu":"其他","hasVip":0,"count":26.0,"pubComp":"HR • 张思琪","salary":"面议","hasComment":1,"jobHref":"//job.dajie.com/3170d696-3999-4fb7-8026-631cb0f7429d.html?jobsearch\u003d0\u0026pagereferer\u003dblank\u0026keyword\u003dnull\u0026clicktype\u003djob","compName":"阳光保险集团","pubCity":"宁波","compHref":"//sinosig.dajie.com?clicktype\u003dname\u0026jobsearch\u003d0\u0026pagereferer\u003dblank\u0026keyword\u003dnull","pubEx":"不限","hasIcon":0,"commentHref":"//www.dajie.com/corp/1015298/comment?jobsearch\u003d0\u0026pagereferer\u003dblank\u0026keyword\u003dnull","time":"2016-10-12","liHref":"//job.dajie.com/3170d696-3999-4fb7-8026-631cb0f7429d.html?jobsearch\u003d0\u0026pagereferer\u003dblank\u0026keyword\u003dnull\u0026clicktype\u003dblank","imgSrc":"//f1.dajieimg.com/n/corp_square_logo/T1HREvB_DT1RXrhCrK_m.jpg"},{"jobName":"顾问助理","logoHref":"//www.dajie.com/corp/3630326?clicktype\u003dlogo\u0026jobsearch\u003d0\u0026pagereferer\u003dblank\u0026keyword\u003dnull","levelRate":100.0,"pubEdu":"本科","hasVip":0,"count":1.0,"pubComp":"猎头 • 高静","salary":"3000及以上元/月","hasComment":1,"jobHref":"//job.dajie.com/85cb0b06-538a-45bf-8b76-483a9962ff97.html?jobsearch\u003d0\u0026pagereferer\u003dblank\u0026keyword\u003dnull\u0026clicktype\u003djob","compName":"上海仲望企业管理咨询有限公司","pubCity":"宁波","compHref":"//www.dajie.com/corp/3630326?clicktype\u003dname\u0026jobsearch\u003d0\u0026pagereferer\u003dblank\u0026keyword\u003dnull","pubEx":"不限","hasIcon":3,"commentHref":"//www.dajie.com/corp/3630326/comment?jobsearch\u003d0\u0026pagereferer\u003dblank\u0026keyword\u003dnull","time":"2016-10-12","liHref":"//job.dajie.com/85cb0b06-538a-45bf-8b76-483a9962ff97.html?jobsearch\u003d0\u0026pagereferer\u003dblank\u0026keyword\u003dnull\u0026clicktype\u003dblank","imgSrc":"//fs1.dajie.com/corplogo/50x50.png"},{"jobName":"猎头顾问","logoHref":"//www.dajie.com/corp/3630326?clicktype\u003dlogo\u0026jobsearch\u003d0\u0026pagereferer\u003dblank\u0026keyword\u003dnull","levelRate":100.0,"pubEdu":"专科","hasVip":0,"count":1.0,"pubComp":"猎头 • 高静","salary":"4000及以上元/月","hasComment":1,"jobHref":"//job.dajie.com/5dfe04ce-767b-4f4c-948c-ad43e938f92f.html?jobsearch\u003d0\u0026pagereferer\u003dblank\u0026keyword\u003dnull\u0026clicktype\u003djob","compName":"上海仲望企业管理咨询有限公司","pubCity":"宁波","compHref":"//www.dajie.com/corp/3630326?clicktype\u003dname\u0026jobsearch\u003d0\u0026pagereferer\u003dblank\u0026keyword\u003dnull","pubEx":"2年以上","hasIcon":3,"commentHref":"//www.dajie.com/corp/3630326/comment?jobsearch\u003d0\u0026pagereferer\u003dblank\u0026keyword\u003dnull","time":"2016-10-12","liHref":"//job.dajie.com/5dfe04ce-767b-4f4c-948c-ad43e938f92f.html?jobsearch\u003d0\u0026pagereferer\u003dblank\u0026keyword\u003dnull\u0026clicktype\u003dblank","imgSrc":"//fs1.dajie.com/corplogo/50x50.png"},{"jobName":"古筝老师","logoHref":"//www.dajie.com/corp/5289955?clicktype\u003dlogo\u0026jobsearch\u003d0\u0026pagereferer\u003dblank\u0026keyword\u003dnull","pubEdu":"专科","hasVip":0,"pubComp":"HR • 姚平平","salary":"6000及以上元/月","hasComment":0,"jobHref":"//job.dajie.com/a7beea9f-3384-4b0f-92ab-9a8035a14392.html?jobsearch\u003d0\u0026pagereferer\u003dblank\u0026keyword\u003dnull\u0026clicktype\u003djob","compName":"六艺星空（北京）文化传播有限公司","pubCity":"宁波","compHref":"//www.dajie.com/corp/5289955?clicktype\u003dname\u0026jobsearch\u003d0\u0026pagereferer\u003dblank\u0026keyword\u003dnull","pubEx":"1年以上","hasIcon":0,"time":"2016-10-12","liHref":"//job.dajie.com/a7beea9f-3384-4b0f-92ab-9a8035a14392.html?jobsearch\u003d0\u0026pagereferer\u003dblank\u0026keyword\u003dnull\u0026clicktype\u003dblank","imgSrc":"//fs1.dajie.com/corplogo/50x50.png"},{"jobName":"平台操作经理","logoHref":"//www.dajie.com/corp/3655047?clicktype\u003dlogo\u0026jobsearch\u003d0\u0026pagereferer\u003dblank\u0026keyword\u003dnull","levelRate":100.0,"pubEdu":"本科","hasVip":0,"count":2.0,"pubComp":"HR • 李昱","salary":"6000及以上元/月","hasComment":1,"jobHref":"//job.dajie.com/ee03802a-a558-48a5-a82c-063333e7b9a4.html?jobsearch\u003d0\u0026pagereferer\u003dblank\u0026keyword\u003dnull\u0026clicktype\u003djob","compName":"上海卡行天下供应链管理有限公司","pubCity":"宁波","compHref":"//www.dajie.com/corp/3655047?clicktype\u003dname\u0026jobsearch\u003d0\u0026pagereferer\u003dblank\u0026keyword\u003dnull","pubEx":"不限","hasIcon":0,"commentHref":"//www.dajie.com/corp/3655047/comment?jobsearch\u003d0\u0026pagereferer\u003dblank\u0026keyword\u003dnull","time":"2016-10-12","liHref":"//job.dajie.com/ee03802a-a558-48a5-a82c-063333e7b9a4.html?jobsearch\u003d0\u0026pagereferer\u003dblank\u0026keyword\u003dnull\u0026clicktype\u003dblank","imgSrc":"//fs1.dajie.com/corplogo/50x50.png"},{"jobName":"客服专员","logoHref":"//www.dajie.com/corp/6009888?clicktype\u003dlogo\u0026jobsearch\u003d0\u0026pagereferer\u003dblank\u0026keyword\u003dnull","pubEdu":"专科","hasVip":0,"pubComp":"主管 • 杨先生","salary":"3000-4000元/月","hasComment":0,"jobHref":"//job.dajie.com/6fcf10e1-2fc1-4ec5-970b-32130b1d91eb.html?jobsearch\u003d0\u0026pagereferer\u003dblank\u0026keyword\u003dnull\u0026clicktype\u003djob","compName":"宁波德业日用电器科技有限公司","pubCity":"宁波","compHref":"//www.dajie.com/corp/6009888?clicktype\u003dname\u0026jobsearch\u003d0\u0026pagereferer\u003dblank\u0026keyword\u003dnull","pubEx":"不限","hasIcon":0,"time":"2016-10-12","liHref":"//job.dajie.com/6fcf10e1-2fc1-4ec5-970b-32130b1d91eb.html?jobsearch\u003d0\u0026pagereferer\u003dblank\u0026keyword\u003dnull\u0026clicktype\u003dblank","imgSrc":"//fs1.dajie.com/corplogo/50x50.png"},{"jobName":"理财经理","logoHref":"//www.dajie.com/corp/4638163?clicktype\u003dlogo\u0026jobsearch\u003d0\u0026pagereferer\u003dblank\u0026keyword\u003dnull","pubEdu":"专科","hasVip":0,"pubComp":"HR • 徐妹","salary":"10000及以上元/月","hasComment":0,"jobHref":"//job.dajie.com/a77686b0-7d19-427a-9700-83468a5e66c2.html?jobsearch\u003d0\u0026pagereferer\u003dblank\u0026keyword\u003dnull\u0026clicktype\u003djob","compName":"上海中云资产管理有限公司","pubCity":"宁波","compHref":"//www.dajie.com/corp/4638163?clicktype\u003dname\u0026jobsearch\u003d0\u0026pagereferer\u003dblank\u0026keyword\u003dnull","pubEx":"不限","hasIcon":0,"time":"2016-10-12","liHref":"//job.dajie.com/a77686b0-7d19-427a-9700-83468a5e66c2.html?jobsearch\u003d0\u0026pagereferer\u003dblank\u0026keyword\u003dnull\u0026clicktype\u003dblank","imgSrc":"//fs1.dajie.com/corplogo/50x50.png"},{"jobName":"资深推广专员","logoHref":"//www.dajie.com/corp/6009888?clicktype\u003dlogo\u0026jobsearch\u003d0\u0026pagereferer\u003dblank\u0026keyword\u003dnull","pubEdu":"专科","hasVip":0,"pubComp":"主管 • 杨先生","salary":"8000-10000元/月","hasComment":0,"jobHref":"//job.dajie.com/f71f6747-dcc8-49f3-93f5-c55dd70fd079.html?jobsearch\u003d0\u0026pagereferer\u003dblank\u0026keyword\u003dnull\u0026clicktype\u003djob","compName":"宁波德业日用电器科技有限公司","pubCity":"宁波","compHref":"//www.dajie.com/corp/6009888?clicktype\u003dname\u0026jobsearch\u003d0\u0026pagereferer\u003dblank\u0026keyword\u003dnull","pubEx":"3年以上","hasIcon":0,"time":"2016-10-12","liHref":"//job.dajie.com/f71f6747-dcc8-49f3-93f5-c55dd70fd079.html?jobsearch\u003d0\u0026pagereferer\u003dblank\u0026keyword\u003dnull\u0026clicktype\u003dblank","imgSrc":"//fs1.dajie.com/corplogo/50x50.png"},{"jobName":"高级文案策划","logoHref":"//www.dajie.com/corp/6009888?clicktype\u003dlogo\u0026jobsearch\u003d0\u0026pagereferer\u003dblank\u0026keyword\u003dnull","pubEdu":"本科","hasVip":0,"pubComp":"主管 • 杨先生","salary":"6000-8000元/月","hasComment":0,"jobHref":"//job.dajie.com/76f167aa-51f9-4de7-80a0-c7303ef2fa70.html?jobsearch\u003d0\u0026pagereferer\u003dblank\u0026keyword\u003dnull\u0026clicktype\u003djob","compName":"宁波德业日用电器科技有限公司","pubCity":"宁波","compHref":"//www.dajie.com/corp/6009888?clicktype\u003dname\u0026jobsearch\u003d0\u0026pagereferer\u003dblank\u0026keyword\u003dnull","pubEx":"2年以上","hasIcon":0,"time":"2016-10-12","liHref":"//job.dajie.com/76f167aa-51f9-4de7-80a0-c7303ef2fa70.html?jobsearch\u003d0\u0026pagereferer\u003dblank\u0026keyword\u003dnull\u0026clicktype\u003dblank","imgSrc":"//fs1.dajie.com/corplogo/50x50.png"},{"jobName":"资深设计师","logoHref":"//www.dajie.com/corp/6009888?clicktype\u003dlogo\u0026jobsearch\u003d0\u0026pagereferer\u003dblank\u0026keyword\u003dnull","pubEdu":"专科","hasVip":0,"pubComp":"主管 • 杨先生","salary":"8000-10000元/月","hasComment":0,"jobHref":"//job.dajie.com/dde67776-5cdf-4c1d-a410-fc0220724766.html?jobsearch\u003d0\u0026pagereferer\u003dblank\u0026keyword\u003dnull\u0026clicktype\u003djob","compName":"宁波德业日用电器科技有限公司","pubCity":"宁波","compHref":"//www.dajie.com/corp/6009888?clicktype\u003dname\u0026jobsearch\u003d0\u0026pagereferer\u003dblank\u0026keyword\u003dnull","pubEx":"2年以上","hasIcon":0,"time":"2016-10-12","liHref":"//job.dajie.com/dde67776-5cdf-4c1d-a410-fc0220724766.html?jobsearch\u003d0\u0026pagereferer\u003dblank\u0026keyword\u003dnull\u0026clicktype\u003dblank","imgSrc":"//fs1.dajie.com/corplogo/50x50.png"},{"jobName":"资深运营专员","logoHref":"//www.dajie.com/corp/6009888?clicktype\u003dlogo\u0026jobsearch\u003d0\u0026pagereferer\u003dblank\u0026keyword\u003dnull","pubEdu":"专科","hasVip":0,"pubComp":"主管 • 杨先生","salary":"10000-15000元/月","hasComment":0,"jobHref":"//job.dajie.com/026f4632-6ba6-4014-a085-3b466ece2536.html?jobsearch\u003d0\u0026pagereferer\u003dblank\u0026keyword\u003dnull\u0026clicktype\u003djob","compName":"宁波德业日用电器科技有限公司","pubCity":"宁波","compHref":"//www.dajie.com/corp/6009888?clicktype\u003dname\u0026jobsearch\u003d0\u0026pagereferer\u003dblank\u0026keyword\u003dnull","pubEx":"3年以上","hasIcon":0,"time":"2016-10-12","liHref":"//job.dajie.com/026f4632-6ba6-4014-a085-3b466ece2536.html?jobsearch\u003d0\u0026pagereferer\u003dblank\u0026keyword\u003dnull\u0026clicktype\u003dblank","imgSrc":"//fs1.dajie.com/corplogo/50x50.png"},{"jobName":"销售精英","logoHref":"//www.dajie.com/corp/3842807?clicktype\u003dlogo\u0026jobsearch\u003d0\u0026pagereferer\u003dblank\u0026keyword\u003dnull","pubEdu":"专科","hasVip":0,"pubComp":"主管 • 祝奕华","salary":"3000-5000元/月","hasComment":0,"jobHref":"//job.dajie.com/9ca62e15-0442-4edd-b8ed-8ce886ae0f4e.html?jobsearch\u003d0\u0026pagereferer\u003dblank\u0026keyword\u003dnull\u0026clicktype\u003djob","compName":"宁波有道网络技术有限公司","pubCity":"宁波","compHref":"//www.dajie.com/corp/3842807?clicktype\u003dname\u0026jobsearch\u003d0\u0026pagereferer\u003dblank\u0026keyword\u003dnull","pubEx":"不限","hasIcon":0,"time":"2016-10-12","liHref":"//job.dajie.com/9ca62e15-0442-4edd-b8ed-8ce886ae0f4e.html?jobsearch\u003d0\u0026pagereferer\u003dblank\u0026keyword\u003dnull\u0026clicktype\u003dblank","imgSrc":"//fs1.dajie.com/corplogo/50x50.png"},{"jobName":"会计","logoHref":"//www.dajie.com/corp/3055701?clicktype\u003dlogo\u0026jobsearch\u003d0\u0026pagereferer\u003dblank\u0026keyword\u003dnull","pubEdu":"本科","hasVip":0,"pubComp":"HR • 陈先生","salary":"3000及以上元/月","hasComment":0,"jobHref":"//job.dajie.com/f543938c-3051-4e38-86b2-069737adffc2.html?jobsearch\u003d0\u0026pagereferer\u003dblank\u0026keyword\u003dnull\u0026clicktype\u003djob","compName":"宁波麦博韦尔移动电话有限公司","pubCity":"宁波","compHref":"//www.dajie.com/corp/3055701?clicktype\u003dname\u0026jobsearch\u003d0\u0026pagereferer\u003dblank\u0026keyword\u003dnull","pubEx":"不限","hasIcon":0,"time":"2016-10-12","liHref":"//job.dajie.com/f543938c-3051-4e38-86b2-069737adffc2.html?jobsearch\u003d0\u0026pagereferer\u003dblank\u0026keyword\u003dnull\u0026clicktype\u003dblank","imgSrc":"//fs1.dajie.com/corplogo/50x50.png"},{"jobName":"销售","logoHref":"//www.dajie.com/corp/3842807?clicktype\u003dlogo\u0026jobsearch\u003d0\u0026pagereferer\u003dblank\u0026keyword\u003dnull","pubEdu":"专科","hasVip":0,"pubComp":"主管 • 祝奕华","salary":"3000-5000元/月","hasComment":0,"jobHref":"//job.dajie.com/917420f4-a6fe-44db-bde3-162ff24fbeda.html?jobsearch\u003d0\u0026pagereferer\u003dblank\u0026keyword\u003dnull\u0026clicktype\u003djob","compName":"宁波有道网络技术有限公司","pubCity":"宁波","compHref":"//www.dajie.com/corp/3842807?clicktype\u003dname\u0026jobsearch\u003d0\u0026pagereferer\u003dblank\u0026keyword\u003dnull","pubEx":"不限","hasIcon":0,"time":"2016-10-12","liHref":"//job.dajie.com/917420f4-a6fe-44db-bde3-162ff24fbeda.html?jobsearch\u003d0\u0026pagereferer\u003dblank\u0026keyword\u003dnull\u0026clicktype\u003dblank","imgSrc":"//fs1.dajie.com/corplogo/50x50.png"}],"salary":"薪资范围","nowPage":59}}